{
  "密封放射源及密封γ放射源容器放射防护检测": [
    "GBZ114—2006",
    "/",
    "/",
    "/",
    "GBZ 114—2006密封放射源及密封γ放射源容 器的放射卫生防护标准"
  ],
  "X射线衍射仪和荧光分析仪工作场所放射防护检测": [
    "GBZ115—2023",
    "/",
    "/",
    "/",
    "GBZ 115—2023低能射线装置放射防护标准"
  ],
  "工业射线探伤放射防护检测": [
    "GBZ117—2022",
    "/",
    "/",
    "/",
    "GBZ 117—2022工业探伤放射防护标准"
  ],
  "含密封源仪表放射防护检测": [
    "GBZ125—2009",
    "/",
    "/",
    "/",
    "GBZ 125—2009含密封源仪表的放射卫生防护 要求"
  ],
  "行李包、车辆、集装箱 等射线安全检查系统放射防护检测": [
    "GBZ127—2002；GBZ143—2015；GBZ130—2020",
    "/",
    "/",
    "/",
    "GBZ 127—2002X射线行李包检查系统卫生防护标准|GBZ 143—2015货物/车辆辐射检查系统的放射防护要求|GBZ 130—2020放射诊断放射防护要求"
  ],
  "加速器放射防护检测": [
    "GBZ141—2002",
    "/",
    "/",
    "/",
    "GBZ 141—2002 γ射线和电子束辐照装置防护 检测规范"
  ],
  "锂": [
    "GBZ/T160.11—2004",
    "样品在室温下至少可保存7d",
    "微孔滤膜",
    "短时间:5L/min; 长时间:1L/min; 个体:1L/min",
    ""
  ],
  "镍": [
    "GBZ/T160.16—2004",
    "样品在室温下可长期保存",
    "微孔滤膜",
    "短时间:5L/min; 长时间:1L/min; 个体:1L/min",
    ""
  ],
  "氨": [
    "GBZ/T160.29—2004",
    "样品尽量在当天测定",
    "大型气泡吸收管 | 显色剂:纳氏试剂",
    "短时间:0.5L/min",
    "GBZ/T 160.29—2004工作场所空气有毒物质测定/无机含氮化合物/4.氨的纳氏试剂分光光度法"
  ],
  "磷化氢": [
    "GBZ/T160.30—2004",
    "样品尽量在当天测定",
    "多孔玻板吸收管 | 显色剂:钼酸铵",
    "短时间:1L/min",
    "GBZ/T160.30—2004 工作场所空气有毒物质测定 无机含磷化合物/5.磷化氢的钼酸铵分光光度法"
  ],
  "磷酸": [
    "GBZ/T160.30—2004",
    "样品在室温下可保存3d",
    "微孔滤膜",
    "短时间:5L/min; 长时间:1L/min; 个体:1L/min",
    "GBZ/T 160.30—2004 工作场所空气有毒物质测定 无机含磷化合物/3.磷酸的钼酸铵分光光度法"
  ],
  "二氧化硫": [
    "GBZ/T160.33—2004",
    "样品在4℃冰箱内可保存7d",
    "多孔玻板吸收管 | 显色剂:盐酸副玫瑰苯胺",
    "短时间:0.5L/min",
    "GBZ/T 160.33—2004 工作场所空气有毒物质测定 硫化物/3.二氧化硫的四氯汞钾—盐酸副玫瑰苯胺分光光度法|GBZ/T 160.33—2004 工作场所空气有毒物质测定 硫化物/4.二氧化硫的甲醛缓冲液－盐酸副玫瑰苯胺分光光度法"
  ],
  "硫化氢": [
    "GBZ/T160.33—2004；GDOHTQC008—2022",
    "样品至少可保存5d",
    "多孔玻板吸收管 | 显色剂:硝酸银",
    "短时间:0.5L/min",
    "GBZ/T 160.33—2004 工作场所空气有毒物质测定 硫化物/7.硫化氢的硝酸银比色法|GDOHTQC008—2022 工作场所空气中硫化氢的亚甲基蓝-分光光度法"
  ],
  "氟化物": [
    "GBZ/T160.36—2004",
    "在室温下至少可稳定7d",
    "浸渍玻璃纤维滤纸 | 浸渍液:碱性溶液",
    "短时间:5L/min; 长时间:1L/min; 个体:1L/min",
    ""
  ],
  "氯": [
    "GBZ/T160.37—2004",
    "样品应在48h内测定",
    "大型气泡吸收管 | 显色剂:甲基橙",
    "短时间:0.5L/min",
    "GBZ/T 160.37—2004 工作场所空气有毒物质测定 氯化物/3.氯气的甲基橙分光光度法"
  ],
  "氯化物": [
    "GBZ/T160.37—2004",
    "在室温下样品可保存7d",
    "多孔玻板吸收管 | 吸收液:碱性溶液",
    "短时间:1L/min",
    ""
  ],
  "萘": [
    "GBZ/T160.44—2004",
    "样品在室温下可保存3d",
    "活性炭管，溶剂解吸型 | 解吸液:二硫化碳",
    "短时间:0.2L/min; 长时间:0.05L/min; 个体:0.05L/min",
    "GBZ/T 160.44—2004 工作场所空气有毒物质测定 多环芳香烃化合物/3.萘的溶剂解吸-气相色谱法"
  ],
  "1,2,3-三氯丙烷": [
    "GBZ/T160.45—2007",
    "样品在室温下可保存7d",
    "活性炭管，溶剂解吸型 | 解吸液:二硫化碳",
    "短时间:0.3L/min; 长时间:0.05L/min; 个体:0.05L/min",
    "GBZ/T 160.45—2007 工作场所空气有毒物质测定 卤代烷烃类化合物/3.1,2,3-三氯丙烷的溶剂解吸-气相色谱法"
  ],
  "1,2-二氯丙烷": [
    "GBZ/T160.45—2007",
    "样品在4℃冰箱中可保存10d",
    "活性炭管，溶剂解吸型 | 解吸液:二硫化碳",
    "短时间:0.2L/min; 长时间:0.03L/min; 个体:0.03L/min",
    "GBZ/T 160.45—2007 工作场所空气有毒物质测定 卤代烷烃类化合物/7.1,2-二氯丙烷的溶剂解吸-气相色谱法"
  ],
  "1,2-二氯乙烷": [
    "GBZ/T160.45—2007",
    "样品在室温下可保存7d",
    "活性炭管，溶剂解吸型 | 解吸液:二硫化碳",
    "短时间:0.3L/min; 长时间:0.05L/min; 个体:0.05L/min",
    "GBZ/T 160.45—2007 工作场所空气有毒物质测定 卤代烷烃类化合物/3.1,2-二氯乙烷的溶剂解吸-气相色谱法|GBZ/T 160.45—2007 工作场所空气有毒物质测定 卤代烷烃类化合物/5.1,2-二氯乙烷的无泵型采样器-气相色谱法"
  ],
  "碘甲烷": [
    "GBZ/T160.45—2007",
    "样品置4℃冰箱内可保存7d",
    "多孔玻板吸收管 | 显色剂:1,2-萘醌-4-磺酸钠",
    "短时间:0.5L/min",
    "GBZ/T 160.45—2007 工作场所空气有毒物质测定卤代烷烃类化合物/6.碘甲烷的1,2-萘醌-4-磺酸钠分光光度法"
  ],
  "二丙酮醇": [
    "GBZ/T160.48—2007",
    "样品在室温下可保存7d",
    "活性炭管，溶剂解吸型 | 解吸液:异戊醇的二硫化碳溶液(1.5%)",
    "短时间:0.1L/min; 长时间:0.05L/min",
    "GBZ/T 160.48—2007 工作场所空气有毒物质测定醇类化合物/3.二丙酮醇的溶剂解吸-气相色谱法"
  ],
  "乙硫醇": [
    "GBZ/T160.49—2004",
    "样品在室温下避光保存可稳定7d",
    "浸渍玻璃纤维滤纸 | 洗脱液:二氯甲烷",
    "短时间:1L/min; 长时间:1L/min; 个体:1L/min",
    "GBZ/T 160.49—2004工作场所空气有毒物质测定 硫醇类化合物/3.乙硫醇的溶剂洗脱﹣气相色谱法|GBZ/T 160.49—2004工作场所空气有毒物质测定 硫醇类化合物/4.乙硫醇的对氨基二甲基苯胺分光光度法"
  ],
  "甲硫醇": [
    "GBZ/T160.49—2004",
    "样品在室温下避光保存可稳定7d",
    "浸渍玻璃纤维滤纸 | 洗脱液:二氯甲烷",
    "短时间:1L/min; 长时间:1L/min; 个体:1L/min",
    "GBZ/T 160.49—2004 工作场所空气有毒物质测定硫醇类化合物/3.甲硫醇的溶剂洗脱－气相色谱法"
  ],
  "2-丁氧基乙醇": [
    "GBZ/T160.50—2004；GDOHTQC033—2024",
    "样品室温下至少可保存14d",
    "活性炭管，溶剂解吸型",
    "短时间:0.3L/min; 长时间:0.05L/min; 个体:0.05L/min",
    "GBZ/T 160.50—2004 工作场所空气有毒物质测定 烷氧基乙醇类化合物/3. 2-甲氧基乙醇、2-乙氧基乙醇和2-丁氧基乙醇的溶剂解吸－气相色谱法 |GDOHTQC 033—2024工作场所空气中3种烷氧基乙醇类化合物的溶剂解吸-气相色谱法"
  ],
  "2-甲氧基乙醇": [
    "GBZ/T160.50—2004；GDOHTQC033—2024",
    "样品室温下至少可保存14d",
    "活性炭管，溶剂解吸型",
    "短时间:0.3L/min; 长时间:0.05L/min; 个体:0.05L/min",
    "GBZ/T 160.50—2004 工作场所空气有毒物质测定 烷氧基乙醇类化合物/3.2-甲氧基乙醇的溶剂解吸－气相色谱法|GDOHTQC 033—2024工作场所空气中3种烷氧基乙醇类化合物的溶剂解吸-气相色谱法"
  ],
  "酚": [
    "GBZ/T160.51—2007",
    "样品在室温下至少可保存10d",
    "硅胶管，溶剂解吸型",
    "短时间:0.3L/min; 长时间:0.05L/min; 个体:0.05L/min",
    "GBZ/T 160.51—2007 工作场所空气有毒物质测定 酚类化合物/3.苯酚的溶剂解吸-气相色谱法|GBZ/T 160.51—2007 工作场所空气有毒物质测定 酚类化合物/4.苯酚的4-氨基安替比林分光光度法"
  ],
  "乙醚": [
    "GBZ/T160.52—2007",
    "样品在室温下可保存7d",
    "活性炭管，热解吸型 | 热解吸",
    "短时间:0.2L/min; 长时间:0.05L/min; 个体:0.05L/min",
    "GBZ/T 160.52—2007 工作场所空气有毒物质测定 脂肪族醚类化合物/3.乙醚的热解吸-气相色谱法"
  ],
  "丙烯醛": [
    "GBZ/T160.54—2007",
    "样品应在24h内测定",
    "注射器 | 直接进样",
    "注射器法，无泵流量",
    "GBZ/T 160.54—2007 工作场所空气有毒物质测定 脂肪族醛类化合物/4.丙烯醛的直接进样-气相色谱法"
  ],
  "异佛尔酮": [
    "GBZ/T160.55—2007",
    "样品在4℃冰箱中可保存10d",
    "活性炭管，溶剂解吸型 | 解吸液:二硫化碳",
    "短时间:0.2L/min",
    "GBZ/T 160.55—2007 工作场所空气有毒物质测定 脂肪族酮类化合物/5.异佛尔酮的溶剂解吸-气相色谱法"
  ],
  "环己酮": [
    "GBZ/T160.56—2004",
    "样品在室温下可保存7d",
    "活性炭管，溶剂解吸型 | 解吸液:二硫化碳",
    "短时间:0.1L/min; 长时间:0.05L/min; 个体:0.05L/min",
    "GBZ/T 160.56—2004 工作场所空气有毒物质测定脂环酮和芳香族酮类化合物/3.环己酮的溶剂解吸-气相色谱法"
  ],
  "环氧丙烷": [
    "GBZ/T160.58—2004",
    "当日应尽快测定",
    "注射器 | 直接进样",
    "注射器法，无泵流量",
    "GBZ/T 160.58—2004 工作场所空气有毒物质测定 环氧化合物/3.环氧乙烷、环氧丙烷和环氧氯丙烷的直接进样—气相色谱法"
  ],
  "环氧乙烷": [
    "GBZ/T160.58—2004",
    "当日应尽快测定",
    "注射器 | 直接进样",
    "注射器法，无泵流量",
    "GBZ/T 160.58—2004 工作场所空气有毒物质测定 环氧化合物/3.环氧乙烷、环氧丙烷和环氧氯丙烷的直接进样—气相色谱法"
  ],
  "环氧氯丙烷": [
    "GBZ/T160.58—2004",
    "当日应尽快测定",
    "注射器 | 直接进样",
    "注射器法，无泵流量",
    "GBZ/T 160.58—2004 工作场所空气有毒物质测定 环氧化合物/3.环氧乙烷、环氧丙烷和环氧氯丙烷的直接进样—气相色谱法"
  ],
  "丙烯酸": [
    "GBZ/T160.59—2004",
    "样品在室温下至少可保存15d",
    "硅胶管，溶剂解吸型 | 解吸液:丙酮",
    "短时间:1L/min; 长时间:0.05L/min; 个体:0.05L/min",
    "GBZ/T 160.59—2004工作场所空气有毒物质测定羧酸类化合物/3.甲酸、乙酸、丙酸、丙烯酸或氯乙酸的溶剂解吸-气相色谱法"
  ],
  "丙酸": [
    "GBZ/T160.59—2004",
    "样品在室温下至少可保存15d",
    "硅胶管，溶剂解吸型 | 解吸液:丙酮",
    "短时间:1L/min; 长时间:0.05L/min; 个体:0.05L/min",
    "GBZ/T 160.59—2004工作场所空气有毒物质测定狻酸类化合物/3．丙酸的溶剂解吸－气相色谱法"
  ],
  "N,N-二甲基乙酰胺": [
    "GBZ/T160.62—2004；GDOHTQC015—2023",
    "样品在室温下可保存7d",
    "多孔玻板吸收管 | 直接进样",
    "短时间:1L/min",
    "GBZ/T 160.62—2004 工作场所空气有毒物质测定 酰胺类化合物/3.N,N-二甲基乙酰胺的溶液采集－气相色谱法|GDOHTQC 015—2023 工作场所空气中二甲基甲酰胺和二甲基乙酰胺的溶剂解吸-气相色谱法"
  ],
  "N,N-二甲基甲酰胺": [
    "GBZ/T160.62—2004；GDOHTQC015—2023",
    "样品在室温下可保存7d",
    "多孔玻板吸收管 | 直接进样",
    "短时间:1L/min",
    "GBZ/T 160.62—2004 工作场所空气有毒物质测定 酰胺类化合物/3.N,N-二甲基甲酰胺的溶液采集－气相色谱法|GDOHTQC 015—2023 工作场所空气中二甲基甲酰胺和二甲基乙酰胺的溶剂解吸-气相色谱法"
  ],
  "丙烯酰胺": [
    "GBZ/T160.62—2004",
    "样品在室温下可保存7d",
    "冲击式吸收管 | 直接进样",
    "短时间:1L/min",
    "GBZ/T 160.62—2004工作场所空气有毒物质测定 酰胺类化合物/3．二甲基甲酰胺、二甲基乙酰胺和丙烯酰胺的溶液采集－气相色谱法"
  ],
  "乙酸丁酯": [
    "GBZ/T160.63—2007",
    "样品在室温下至少可保存7d",
    "活性炭管，溶剂解吸型 | 解吸液:二硫化碳",
    "短时间:0.1L/min; 长时间:0.05L/min; 个体:0.05L/min",
    "GBZ/T 160.63—2007 工作场所空气有毒物质测定 饱和脂肪族脂类化合物/3.乙酸丁酯的溶剂解吸-气相色谱法"
  ],
  "乙酸丙酯": [
    "GBZ/T160.63—2007",
    "样品在室温下至少可保存7d",
    "活性炭管，溶剂解吸型 | 解吸液:二硫化碳",
    "短时间:0.1L/min; 长时间:0.05L/min; 个体:0.05L/min",
    "GBZ/T 160.63—2007 工作场所空气有毒物质测定 饱和脂肪族脂类化合物/3.乙酸丙酯的溶剂解吸-气相色谱法"
  ],
  "乙酸乙酯": [
    "GBZ/T160.63—2007",
    "样品在室温下至少可保存7d",
    "活性炭管，溶剂解吸型 | 解吸液:二硫化碳",
    "短时间:0.1L/min; 长时间:0.05L/min; 个体:0.05L/min",
    "GBZ/T 160.63—2007 工作场所空气有毒物质测定 饱和脂肪族脂类化合物/3.乙酸乙酯的溶剂解吸-气相色谱法|GBZ/T 160.63—2007 工作场所空气有毒物质测定 饱和脂肪族脂类化合物/4.乙酸乙酯的无泵型采样-气相色谱法"
  ],
  "乙酸甲酯": [
    "GBZ/T160.63—2007",
    "样品在室温下至少可保存7d",
    "活性炭管，溶剂解吸型 | 解吸液:二硫化碳",
    "短时间:0.1L/min; 长时间:0.05L/min; 个体:0.05L/min",
    "GBZ/T 160.63—2007 工作场所空气有毒物质测定 饱和脂肪族脂类化合物/3.乙酸甲酯的溶剂解吸-气相色谱法"
  ],
  "乙酸乙烯酯": [
    "GBZ/T160.64—2004；GDOHTQC034—2024",
    "样品在室温下可保存7d",
    "活性炭管，热解吸型 | 热解吸",
    "短时间:0.1L/min; 长时间:0.05L/min; 个体:0.05L/min",
    "GBZ/T 160.64—2004 工作场所空气有毒物质测定 不饱和脂肪族酯类化合物/4.乙酸乙烯酯的热解吸－气相色谱法 |GDOHTQC 034—2024工作场所空气中乙酸乙烯酯的溶剂解吸-气相色谱法"
  ],
  "苯胺": [
    "GBZ/T160.72—2004",
    "样品在室温下至少可保存7d",
    "硅胶管，溶剂解吸型 | 显色剂:苯胺",
    "短时间:0.2L/min; 长时间:0.05L/min; 个体:0.05L/min",
    "GBZ/T 160.72—2004工作场所空气有毒物质测定芳香族胺类化合物/3.苯胺的溶剂解吸—气相色谱法"
  ],
  "氯化苦": [
    "GBZ/T160.73—2004",
    "应当天测定完毕",
    "多孔玻板吸收管 | 显色剂:对氨基苯磺酸",
    "短时间:0.25L/min",
    "GBZ/T 160.73—2004 工作场所空气有毒物质测定 硝基烷烃类化合物/3.氯化苦的盐酸萘乙二胺分光光度法"
  ],
  "四氢呋喃": [
    "GBZ/T160.75—2004；GDOHTQC004—2021",
    "样品在冰箱内可保存7d",
    "401有机担体管，溶剂解吸型 | 解吸液:二硫化碳",
    "短时间:0.1L/min; 长时间:0.05L/min; 个体:0.05L/min",
    "GBZ/T 160.75—2004工作场所空气有毒物质测定 杂环化合物/3.四氢呋喃和吡啶的溶剂解吸一气相色谱法|GDOHTQC 004—2021 工作场所空气中四氢呋喃的溶剂解吸-气相色谱法"
  ],
  "体力劳动强度分级": [
    "GBZ/T189.10—2007",
    "/",
    "直读 | 直读",
    "直读",
    ""
  ],
  "超高频辐射": [
    "GBZ/T189.1—2007",
    "/",
    "直读 | 直读",
    "直读",
    "GBZ/T 189.1—2007 工作场所物理因素测量 第1部分：超高频辐射"
  ],
  "体力劳动时的心率": [
    "GBZ/T189.11—2007",
    "/",
    "直读 | 直读",
    "直读",
    ""
  ],
  "高频电磁场": [
    "GBZ/T189.2—2007",
    "/",
    "直读 | 直读",
    "直读",
    "GBZ/T 189.2—2007 工作场所物理因素测量 第2部分：高频电磁场"
  ],
  "1Hz~100kHz电场": [
    "GBZ/T189.3—2018",
    "/",
    "直读 | 直读",
    "直读",
    ""
  ],
  "磁场": [
    "GBZ/T189.3—2018",
    "/",
    "直读 | 直读",
    "直读",
    ""
  ],
  "激光辐射": [
    "GBZ/T189.4—2007",
    "/",
    "直读 | 直读",
    "直读",
    ""
  ],
  "微波辐射": [
    "GBZ/T189.5—2007",
    "/",
    "直读 | 直读",
    "直读",
    "GBZ/T 189.5—2007 工作场所物理因素测量 第5部分：微波辐射"
  ],
  "紫外辐射": [
    "GBZ/T189.6—2007",
    "/",
    "直读 | 直读",
    "直读",
    "GBZ/T 189.6—2007 工作场所物理因素测量 第6部分：紫外辐射"
  ],
  "高温": [
    "GBZ/T189.7—2007",
    "/",
    "直读 | 直读",
    "直读",
    "GBZ/T 189.7—2007 工作场所物理因素测量 第7部分：高温"
  ],
  "噪声": [
    "GBZ/T189.8—2007",
    "/",
    "直读",
    "直读",
    "mobile_individual",
    "6h",
    1,
    "GBZ/T 189.8—2007 工作场所物理因素测量 第8部分：噪声"
  ],
  "手传振动": [
    "GBZ/T189.9—2025",
    "/",
    "直读 | 直读",
    "直读",
    "GBZ/T 189.9—2007 工作场所物理因素测量 第9部分：手传振动"
  ],
  "总粉尘浓度": [
    "GBZ/T192.1—2025",
    "/",
    "丙纶滤膜",
    "短时间:15L/min~40L/min; 长时间:1L/min~5L/min",
    ""
  ],
  "呼吸性粉尘浓度": [
    "GBZ/T192.2—2025",
    "/",
    "丙纶滤膜",
    "短时间:2L/min; 长时间:1L/min~5L/min",
    ""
  ],
  "粉尘分散度": [
    "GBZ/T192.3—2007",
    "/",
    "丙纶滤膜 | 滤膜溶解涂片",
    "短时间:15L/min~40L/min",
    "GBZ/T 192.3—2007 工作场所空气中粉尘测定 第3部分：粉尘分散度/3.粉尘分散度的滤膜溶解涂片法"
  ],
  "粉尘中游离二氧化硅": [
    "GBZ/T192.4—2007",
    "/",
    "丙纶滤膜 | 焦磷酸法",
    "短时间:15L/min~40L/min",
    "GBZ/T 192.4—2007 工作场所空气中粉尘测定 第 4 部分：游离二氧化硅含量/3.粉尘中游离二氧化硅的焦磷酸法"
  ],
  "石棉纤维": [
    "GBZ/T192.5—2007",
    "/",
    "丙纶滤膜 | 滤膜-相差显微镜",
    "短时间:1L/min~2L/min",
    "GBZ/T 192.5—2007 工作场所空气中粉尘测定 第 5 部分：石棉纤维浓度/3.石棉纤维的滤膜-相差显微镜法"
  ],
  "二甲氧基甲烷": [
    "GBZ/T300.100—2018",
    "样品在室温下可保存5d",
    "活性炭管，溶剂解吸型 | 解吸液:正己烷",
    "短时间:0.1L/min; 长时间:0.02L/min",
    "GBZ/T 300.100—2018 工作场所空气有毒物质测定 第100部分：糠醛和二甲氧基甲烷/5.二甲氧基甲烷的溶剂解吸-气相色谱法|GDOHTQC 035—2024工作场所空气中二甲氧基甲烷的溶剂解吸-气相色谱法"
  ],
  "糠醛": [
    "GBZ/T300.100—2018",
    "样品应在24h内测定",
    "多孔玻板吸收管 | 显色剂:苯胺",
    "短时间:0.5L/min",
    "GBZ/T 300.100—2018 工作场所空气有毒物质测定 第100部分：糠醛和二甲氧基甲烷/4.糠醛的溶液吸收-苯胺分光光度法"
  ],
  "钴": [
    "GBZ/T300.10—2017",
    "样品在室温下可长期保存",
    "微孔滤膜 | 酸消解",
    "短时间:5L/min",
    ""
  ],
  "三氯乙醛": [
    "GBZ/T300.101—2017",
    "样品在室温下可保存7d",
    "GDX-502管，溶剂解吸型 | 解吸液:乙腈",
    "短时间:0.2L/min",
    ""
  ],
  "丁酮": [
    "GBZ/T300.103—2017",
    "样品在室温下可保存7d",
    "活性炭管，溶剂解吸型 | 解吸液:二硫化碳",
    "短时间:0.1L/min; 长时间:0.05L/min",
    ""
  ],
  "丙酮": [
    "GBZ/T300.103—2017",
    "样品在室温下可保存7d",
    "活性炭管，溶剂解吸型 | 解吸液:二硫化碳",
    "短时间:0.1L/min; 长时间:0.05L/min",
    "GBZ/T 300.103—2017工作场所空气有毒物质测定第103部分：丙酮、丁酮和甲基异丁基甲酮/4.丙酮、丁酮和甲基异丁基甲酮的溶剂解吸-气相色谱法|GBZ/T 300.103—2017工作场所空气有毒物质测定第103部分：丙酮、丁酮和甲基异丁基甲酮/5.丙酮的热解吸-气相色谱法"
  ],
  "甲基异丁基甲酮": [
    "GBZ/T300.103—2017",
    "样品在室温下可保存7d",
    "活性炭管，溶剂解吸型 | 解吸液:二硫化碳",
    "短时间:0.1L/min; 长时间:0.05L/min",
    ""
  ],
  "2-己酮": [
    "GBZ/T300.104—2017",
    "样品在室温下可保存10d",
    "活性炭管，溶剂解吸型 | 解吸液:二硫化碳",
    "短时间:0.1L/min; 长时间:0.05L/min",
    "GBZ/T 300.104—2017工作场所空气有毒物质测定第104部分：二乙基甲酮、2-己酮和二异丁基甲酮/4.2-己酮的的溶剂解吸-气相色谱法"
  ],
  "二乙基甲酮": [
    "GBZ/T300.104—2017",
    "样品在室温下可保存10d",
    "活性炭管，溶剂解吸型 | 解吸液:二硫化碳",
    "短时间:0.1L/min; 长时间:0.05L/min",
    ""
  ],
  "二异丁基甲酮": [
    "GBZ/T300.104—2017",
    "样品在室温下可保存10d",
    "活性炭管，溶剂解吸型 | 解吸液:二硫化碳",
    "短时间:0.1L/min; 长时间:0.05L/min",
    "GBZ/T 300.104—2017工作场所空气有毒物质测定第104部分：二乙基甲酮、2-己酮和二异丁基甲酮/4.二异丁基甲酮的溶剂解吸-气相色谱法"
  ],
  "氯丙酮": [
    "GBZ/T300.106—2018",
    "样品在室温下可保存3d",
    "硅胶管，溶剂解吸型 | 解吸液:丙酮-正己烷",
    "短时间:0.2L/min",
    "GBZ/T 300.106—2018 工作场所空气有毒物质测定 第106部分：氯丙酮/4.氯丙酮的溶剂解吸-气相色谱法"
  ],
  "氢醌": [
    "GBZ/T300.110—2017",
    "样品在室温下可保存7d",
    "微孔滤膜 | 解吸液:水",
    "短时间:5L/min; 长时间:1L/min",
    ""
  ],
  "铜": [
    "GBZ/T300.11—2017",
    "样品在室温下可长期保存",
    "微孔滤膜 | 酸消解",
    "短时间:5L/min; 长时间:1L/min",
    ""
  ],
  "间苯二酚": [
    "GBZ/T300.110—2017",
    "样品应尽快测定",
    "多孔玻板吸收管 | 显色剂:碳酸钠",
    "短时间:0.5L/min",
    "GBZ/T 300.130—2017 工作场所空气有毒物质测定 第 110 部分：氢醌和间苯二酚/5.间苯二酚的溶液吸收-碳酸钠分光光度法"
  ],
  "乙酸": [
    "GBZ/T300.112—2017",
    "样品在室温下可保存15d",
    "硅胶管，溶剂解吸型 | 解吸液:丙酮",
    "短时间:0.3L/min; 长时间:0.05L/min",
    "GBZ/T 300.112—2017 工作场所空气有毒物质测定 第 112 部分：甲酸和乙酸/5.乙酸的溶剂解吸-气相色谱法"
  ],
  "甲酸": [
    "GBZ/T300.112—2017",
    "样品在室温下可保存7d",
    "浸渍硅胶管，溶剂解吸型 | 解吸液:硫酸溶液",
    "短时间:0.3L/min; 长时间:0.05L/min",
    "GBZ/T 300.112—2017 工作场所空气有毒物质测定 第112部分：甲酸和乙酸/4.甲酸的溶剂解吸-顶空气相色谱法"
  ],
  "对苯二甲酸": [
    "GBZ/T300.114—2017",
    "样品在室温下可保存7d",
    "微孔滤膜 | 解吸液:水",
    "短时间:2L/min; 长时间:1L/min",
    ""
  ],
  "草酸": [
    "GBZ/T300.114—2017",
    "样品应尽快测定",
    "多孔玻板吸收管 | 直接进样",
    "短时间:0.5L/min",
    ""
  ],
  "氯乙酸": [
    "GBZ/T300.115—2017",
    "样品在室温下可保存15d",
    "硅胶管，溶剂解吸型 | 解吸液:水",
    "短时间:1L/min",
    ""
  ],
  "对甲苯磺酸": [
    "GBZ/T300.116—2018",
    "样品在室温下可保存7d",
    "浸渍超细玻璃纤维滤纸 | 解吸液:异丙醇溶液",
    "短时间:2L/min; 长时间:1L/min",
    ""
  ],
  "乙酐": [
    "GBZ/T300.118—2017",
    "样品在室温下可保存7d",
    "活性炭管，溶剂解吸型 | 解吸液:丙酮",
    "短时间:0.2L/min; 长时间:0.05L/min",
    "GBZ/T 300.118—2017 工作场所空气有毒物质测定 第 118 部分：乙酸酐、马来酸酐和邻苯二甲酸酐/4.乙酸酐的溶剂解吸-气相色谱法"
  ],
  "乙酸酐": [
    "GBZ/T300.118—2017",
    "样品在室温下可保存7d",
    "活性炭管，溶剂解吸型 | 解吸液:丙酮",
    "短时间:0.2L/min; 长时间:0.05L/min",
    ""
  ],
  "邻苯二甲酸酐": [
    "GBZ/T300.118—2017",
    "样品在室温下可保存7d",
    "玻璃纤维滤纸 | 洗脱液:丙酮",
    "短时间:2L/min",
    "GBZ/T 300.118—2017 工作场所空气有毒物质测定 第118部分：乙酸酐、马来酸酐和邻苯二甲酸酐/6.邻苯二甲酸酐的溶剂洗脱-气相色谱法"
  ],
  "马来酸酐": [
    "GBZ/T300.118—2017",
    "样品在室温下可保存3d",
    "多孔玻板吸收管 | 直接进样",
    "短时间:1L/min",
    ""
  ],
  "甲酸乙酯": [
    "GBZ/T300.122—2017",
    "样品在室温下可保存5d",
    "活性炭管，溶剂解吸型",
    "短时间:0.1L/min; 长时间:0.05L/min",
    ""
  ],
  "甲酸甲酯": [
    "GBZ/T300.122—2017",
    "样品在室温下可保存5d",
    "活性炭管，溶剂解吸型",
    "短时间:0.1L/min; 长时间:0.05L/min",
    ""
  ],
  "三甲苯磷酸酯": [
    "GBZ/T300.126—2017",
    "样品在冰箱内可保存24h",
    "超细玻璃纤维滤纸 | 洗脱液:乙醇",
    "短时间:5L/min; 长时间:1L/min",
    ""
  ],
  "硫酸二甲酯": [
    "GBZ/T300.126—2017",
    "样品在常温下可稳定2d",
    "硅胶管，溶剂解吸型 | 解吸液:丙酮",
    "短时间:0.3L/min; 长时间:0.05L/min",
    ""
  ],
  "丙烯酸正丁酯": [
    "GBZ/T300.127—2017",
    "样品在室温下可保存7d",
    "活性炭管，溶剂解吸型 | 解吸液:二硫化碳",
    "短时间:0.1L/min; 长时间:0.05L/min",
    "GBZ/T 300.127—2017工作场所空气有毒物质测定 第127部分： 丙烯酸酯类/4.丙烯酸正丁酯的溶剂解吸-气相色谱法"
  ],
  "丙烯酸甲酯": [
    "GBZ/T300.127—2017",
    "样品在室温下可保存7d",
    "硅胶管，热解吸型 | 热解吸",
    "短时间:0.1L/min; 长时间:0.05L/min",
    "GBZ/T 300.127—2017工作场所空气有毒物质测定  第127部分：丙烯酸酯类/4.丙烯酸甲酯的溶剂解吸-气相色谱法|GBZ/T 300.127—2017工作场所空气有毒物质测定  第127部分：丙烯酸酯类/5.丙烯酸甲酯的热解吸-气相色谱法"
  ],
  "甲基丙烯酸正丁酯": [
    "GBZ/T300.128—2018",
    "样品在室温下可保存15d",
    "活性炭管，溶剂解吸型 | 解吸液:二硫化碳",
    "短时间:0.2L/min; 长时间:0.05L/min",
    ""
  ],
  "甲基丙烯酸甲酯": [
    "GBZ/T300.128—2018",
    "样品应在24h内测定",
    "采气袋 | 直接进样",
    "采气袋法，无泵流量",
    "GBZ/T 300.128—2018 工作场所空气有毒物质测定 第128部分：甲基丙烯酸酯类/4.甲基丙烯酸甲酯的直接进样-气相色谱法"
  ],
  "甲基丙烯酸缩水甘油酯": [
    "GBZ/T300.128—2018",
    "样品应在24h内测定",
    "大型气泡吸收管 | 直接进样",
    "短时间:0.5L/min",
    ""
  ],
  "氯乙酸乙酯": [
    "GBZ/T300.129—2017",
    "样品在室温下可保存14d",
    "活性炭管，溶剂解吸型 | 解吸液:二硫化碳",
    "短时间:0.2L/min; 长时间:0.05L/min",
    ""
  ],
  "氯乙酸甲酯": [
    "GBZ/T300.129—2017",
    "样品在室温下可保存14d",
    "活性炭管，溶剂解吸型 | 解吸液:二硫化碳",
    "短时间:0.2L/min; 长时间:0.05L/min",
    ""
  ],
  "邻苯二甲酸二丁酯": [
    "GBZ/T300.130—2017",
    "样品可保存15d",
    "硅胶管，溶剂解吸型 | 解吸液:甲醇",
    "短时间:0.2L/min; 长时间:0.05L/min",
    "GBZ/T 300.130—2017 工作场所空气有毒物质测定 第130部分：邻苯二甲酸二丁酯和邻苯二甲酸二辛酯/5.邻苯二甲酸二丁酯的溶剂洗脱-气相色谱法"
  ],
  "邻苯二甲酸二辛酯": [
    "GBZ/T300.130—2017",
    "样品可保存15d",
    "硅胶管，溶剂解吸型 | 解吸液:甲醇",
    "短时间:0.2L/min; 长时间:0.05L/min",
    ""
  ],
  "铟": [
    "GBZ/T300.13—2017",
    "样品在常温下可长期保存",
    "微孔滤膜 | 酸消解",
    "短时间:5L/min; 长时间:1L/min",
    ""
  ],
  "二苯基甲烷二异氰酸酯": [
    "GBZ/T300.132—2017",
    "样品在室温下避光可保存5d；样品在2℃～8℃避光环境中可保存14 天",
    "冲击式吸收管 | 吸收液:酸溶液",
    "短时间:3L/min",
    "GBZ/T 300.132—2017 工作场所空气有毒物质测定 第132部分：甲苯二异氰酸酯、二苯基甲烷二异氰酸酯和异佛尔酮二异氰酸酯/4.二苯基甲烷二异氰酸酯溶液吸收-气相色谱法"
  ],
  "异佛尔酮二异氰酸酯": [
    "GBZ/T300.132—2017",
    "样品在室温下可保存7d",
    "浸渍滤纸 | 浸渍液:吡啶哌嗪溶液",
    "短时间:1L/min; 长时间:1L/min",
    ""
  ],
  "甲苯二异氰酸酯": [
    "GBZ/T300.132—2017",
    "样品在室温下避光可保存5d；样品在2℃～8℃避光环境中可保存14 天",
    "冲击式吸收管 | 吸收液:酸溶液",
    "短时间:3L/min",
    ""
  ],
  "丙烯腈": [
    "GBZ/T300.133—2017",
    "样品在室温下可保存5d",
    "活性炭管，溶剂解吸型 | 解吸液:二硫化碳",
    "短时间:0.5L/min; 长时间:0.05L/min",
    "GBZ/T 300.133—2017工作场所空气有毒物质测定第133部分：乙腈、丙烯腈和甲基丙烯腈/4.丙烯腈的溶剂解吸﹣气相色谱法|GBZ/T 300.133—2017工作场所空气有毒物质测定第133部分：乙腈、丙烯腈和甲基丙烯腈/5．丙烯睛的热解吸﹣气相色谱法"
  ],
  "乙腈": [
    "GBZ/T300.133—2017",
    "样品在室温下可保存5d",
    "活性炭管，溶剂解吸型 | 解吸液:二硫化碳",
    "短时间:0.5L/min; 长时间:0.05L/min",
    "GBZ/T 300.133—2017工作场所空气有毒物质测定  第133部分： 乙腈、丙烯腈和甲基丙烯腈/4.乙腈的溶剂解吸-气相色谱法"
  ],
  "甲基丙烯腈": [
    "GBZ/T300.133—2017",
    "样品在室温下可保存5d",
    "活性炭管，溶剂解吸型 | 解吸液:二硫化碳",
    "短时间:0.5L/min; 长时间:0.05L/min",
    "GBZ/T 300.133—2017 工作场所空气有毒物质测定 第133部分：乙腈、丙烯腈和甲基丙烯腈/4.乙腈、丙烯腈和甲基丙烯腈的溶剂解吸-气相色谱法"
  ],
  "丙酮氰醇": [
    "GBZ/T300.134—2017",
    "样品在室温下可保存7d",
    "大型气泡吸收管 | 显色剂:巴比妥酸",
    "短时间:0.2L/min",
    ""
  ],
  "苄基氰": [
    "GBZ/T300.134—2017",
    "样品在室温下可保存7d",
    "活性炭管，溶剂解吸型 | 解吸液:二硫化碳",
    "短时间:0.2L/min",
    ""
  ],
  "三乙胺": [
    "GBZ/T300.136—2017",
    "样品在室温下可保存7d",
    "硅胶管，溶剂解吸型",
    "短时间:0.5L/min; 长时间:0.05L/min",
    ""
  ],
  "三甲胺": [
    "GBZ/T300.136—2017",
    "样品在室温下可保存7d",
    "硅胶管，溶剂解吸型",
    "短时间:0.5L/min; 长时间:0.05L/min",
    ""
  ],
  "二乙胺": [
    "GBZ/T300.136—2017",
    "样品在室温下可保存7d",
    "硅胶管，溶剂解吸型",
    "短时间:0.5L/min; 长时间:0.05L/min",
    ""
  ],
  "乙二胺": [
    "GBZ/T300.137—2017",
    "样品在室温下可保存15d",
    "硅胶管，溶剂解吸型 | 解吸液:水",
    "短时间:0.2L/min; 长时间:0.05L/min",
    ""
  ],
  "乙胺": [
    "GBZ/T300.137—2017",
    "样品在室温下可保存15d",
    "硅胶管，溶剂解吸型 | 解吸液:水",
    "短时间:0.2L/min; 长时间:0.05L/min",
    "GBZ/T 300.137—2017 工作场所空气有毒物质测定 第 137 部分：乙胺、乙二胺和环己胺/4.溶剂解吸-气相色谱法"
  ],
  "环己胺": [
    "GBZ/T300.137—2017",
    "样品在室温下可保存15d",
    "硅胶管，溶剂解吸型 | 解吸液:水",
    "短时间:0.2L/min; 长时间:0.05L/min",
    ""
  ],
  "乙醇胺": [
    "GBZ/T300.139—2017",
    "样品应在24h内测定",
    "大型气泡吸收管 | 直接进样",
    "短时间:1L/min",
    "GBZ/T 300.139—2017 工作场所空气有毒物质测定 第 139 部分：乙醇胺/4.乙醇胺的溶液吸收-气相色谱法"
  ],
  "偏二甲基肼": [
    "GBZ/T300.140—2017",
    "样品在室温下可保存7d",
    "酸性硅胶管，溶剂解吸型 | 解吸液:硫酸溶液",
    "短时间:1L/min; 长时间:0.05L/min",
    ""
  ],
  "甲基肼": [
    "GBZ/T300.140—2017",
    "样品在室温下可保存7d",
    "酸性硅胶管，溶剂解吸型 | 解吸液:氢氧化钠溶液",
    "短时间:1L/min; 长时间:0.05L/min",
    ""
  ],
  "肼": [
    "GBZ/T300.140—2017",
    "样品在室温下可保存7d",
    "酸性硅胶管，溶剂解吸型 | 解吸液:硫酸溶液",
    "短时间:1L/min; 长时间:0.05L/min",
    "GBZ/T 300.140—2017 工作场所空气有毒物质测定 第140部分：肼、甲基肼和偏二甲基肼/4.肼的溶剂解吸-气相色谱法"
  ],
  "三氯苯胺": [
    "GBZ/T300.142—2017",
    "样品应在24h内测定",
    "冲击式吸收管 | 吸收液:环己烷",
    "短时间:3L/min",
    ""
  ],
  "对硝基苯胺": [
    "GBZ/T300.143—2017",
    "样品在室温下可保存7d",
    "硅胶管，溶剂解吸型 | 解吸液:无水乙醇",
    "短时间:0.2L/min; 长时间:0.05L/min",
    "GBZ/T 300.143—2017 工作场所空气有毒物质测定第143部分：对硝基苯胺/5.对硝基苯胺的溶剂解吸-气相色谱法"
  ],
  "2,4-二硝基氯苯": [
    "GBZ/T300.146—2017",
    "样品在室温下可保存7d",
    "硅胶管，溶剂解吸型",
    "短时间:0.2L/min; 长时间:0.05L/min",
    "GBZ/T 300.146—2017工作场所空气有毒物质测定 第146部分：硝基苯、硝基甲苯和硝基氯苯/4.2,4-二硝基氯苯的气相色谱法"
  ],
  "三硝基甲苯": [
    "GBZ/T300.146—2017",
    "样品在室温下可保存7d",
    "硅胶管，溶剂解吸型",
    "短时间:0.2L/min; 长时间:0.05L/min",
    "GBZ/T 300.146—2017工作场所空气有毒物质测定 第 146 部分：硝基苯、硝基甲苯和硝基氯苯/4.三硝基甲苯的气相色谱法"
  ],
  "二硝基甲苯": [
    "GBZ/T300.146—2017",
    "样品在室温下可保存7d",
    "硅胶管，溶剂解吸型",
    "短时间:0.2L/min; 长时间:0.05L/min",
    "GBZ/T 300.146—2017工作场所空气有毒物质测定 第146部分：硝基苯、硝基甲苯和硝基氯苯/4.二硝基甲苯的气相色谱法"
  ],
  "硝基氯苯": [
    "GBZ/T300.146—2017",
    "样品在室温下可保存7d",
    "硅胶管，溶剂解吸型",
    "短时间:0.2L/min; 长时间:0.05L/min",
    ""
  ],
  "硝基甲苯": [
    "GBZ/T300.146—2017",
    "样品在室温下可保存7d",
    "硅胶管，溶剂解吸型",
    "短时间:0.2L/min; 长时间:0.05L/min",
    "GBZ/T 300.146—2017工作场所空气有毒物质测定 第 146 部分：硝基苯、硝基甲苯和硝基氯苯/4.硝基甲苯的气相色谱法"
  ],
  "硝基苯": [
    "GBZ/T300.146—2017",
    "样品在室温下可保存7d",
    "硅胶管，溶剂解吸型",
    "短时间:0.2L/min; 长时间:0.05L/min",
    "GBZ/T 300.146—2017工作场所空气有毒物质测定 第 146 部分：硝基苯、硝基甲苯和硝基氯苯/4.硝基苯的气相色谱法"
  ],
  "亚胺硫磷": [
    "GBZ/T300.149—2017",
    "样品在冰箱内可保存7d",
    "硅胶管，溶剂解吸型 | 解吸液:丙酮",
    "短时间:0.5L/min; 长时间:0.05L/min",
    ""
  ],
  "倍硫磷": [
    "GBZ/T300.149—2017",
    "样品在冰箱内可保存7d",
    "硅胶管，溶剂解吸型 | 解吸液:丙酮",
    "短时间:0.5L/min; 长时间:0.05L/min",
    ""
  ],
  "杀螟松": [
    "GBZ/T300.149—2017",
    "样品在冰箱内可保存7d",
    "硅胶管，溶剂解吸型 | 解吸液:丙酮",
    "短时间:0.5L/min; 长时间:0.05L/min",
    ""
  ],
  "甲基对硫磷": [
    "GBZ/T300.149—2017",
    "样品在冰箱内可保存7d",
    "硅胶管，溶剂解吸型 | 解吸液:丙酮",
    "短时间:0.5L/min; 长时间:0.05L/min",
    ""
  ],
  "四乙基铅": [
    "GBZ/T300.15—2017",
    "样品应尽快测定",
    "活性炭管，热解吸型 | 酸解吸",
    "短时间:0.3L/min; 长时间:0.05L/min",
    ""
  ],
  "对硫磷": [
    "GBZ/T300.150—2017",
    "样品在4℃冰箱内可保存7d",
    "聚氨酯泡沫塑料采样管，溶剂解吸型 | 解吸液:甲醇",
    "短时间:1L/min; 长时间:0.2L/min",
    ""
  ],
  "敌敌畏": [
    "GBZ/T300.150—2017",
    "样品在4℃冰箱内可保存7d",
    "聚氨酯泡沫塑料采样管，溶剂解吸型 | 解吸液:甲醇",
    "短时间:1L/min; 长时间:0.2L/min",
    ""
  ],
  "甲拌磷": [
    "GBZ/T300.150—2017",
    "样品在4℃冰箱内可保存7d",
    "聚氨酯泡沫塑料采样管，溶剂解吸型 | 解吸液:甲醇",
    "短时间:1L/min; 长时间:0.2L/min",
    ""
  ],
  "铅": [
    "GBZ/T300.15—2017",
    "样品在室温下可长期保存",
    "微孔滤膜 | 酸消解",
    "短时间:5L/min; 长时间:1L/min",
    ""
  ],
  "久效磷": [
    "GBZ/T300.151—2017",
    "样品在冰箱内可保存7d",
    "硅胶管，溶剂解吸型 | 解吸液:丙酮",
    "短时间:0.5L/min; 长时间:0.05L/min",
    ""
  ],
  "异稻瘟净": [
    "GBZ/T300.151—2017",
    "样品在冰箱内可保存7d",
    "硅胶管，溶剂解吸型 | 解吸液:丙酮",
    "短时间:0.5L/min; 长时间:0.05L/min",
    ""
  ],
  "氧乐果": [
    "GBZ/T300.151—2017",
    "样品在冰箱内可保存7d",
    "硅胶管，溶剂解吸型 | 解吸液:丙酮",
    "短时间:0.5L/min; 长时间:0.05L/min",
    ""
  ],
  "内吸磷": [
    "GBZ/T300.153—2017",
    "样品应在24h内测定",
    "多孔玻板吸收管 | 吸收液:甲醇溶液",
    "短时间:1L/min",
    ""
  ],
  "甲基内吸磷": [
    "GBZ/T300.153—2017",
    "样品应在24h内测定",
    "多孔玻板吸收管 | 吸收液:甲醇溶液",
    "短时间:1L/min",
    ""
  ],
  "磷胺": [
    "GBZ/T300.153—2017",
    "样品应在24h内测定",
    "多孔玻板吸收管 | 吸收液:甲醇溶液",
    "短时间:1L/min",
    ""
  ],
  "马拉硫磷": [
    "GBZ/T300.153—2017",
    "样品应在24h内测定",
    "多孔玻板吸收管 | 吸收液:甲醇溶液",
    "短时间:1L/min",
    ""
  ],
  "奥克托今": [
    "GBZ/T300.159—2017",
    "样品在室温下可保存7d",
    "超细玻璃纤维滤纸 | 洗脱液:丙酮",
    "短时间:3L/min; 长时间:1L/min",
    ""
  ],
  "硝化甘油": [
    "GBZ/T300.159—2017",
    "样品在室温下可保存7d",
    "GDX-103管，溶剂解吸型 | 解吸液:无水乙醇",
    "短时间:0.2L/min",
    ""
  ],
  "硝基胍": [
    "GBZ/T300.159—2017",
    "样品在室温下可保存7d",
    "微孔滤膜 | 洗脱液:水",
    "短时间:3L/min; 长时间:1L/min",
    ""
  ],
  "黑索金": [
    "GBZ/T300.159—2017",
    "样品在室温下可保存7d",
    "超细玻璃纤维滤纸 | 洗脱液:丙酮/甲醇",
    "短时间:3L/min; 长时间:1L/min",
    ""
  ],
  "洗衣粉酶": [
    "GBZ/T300.160—2017",
    "样品宜尽快测定",
    "超细玻璃纤维滤纸 | 洗脱液:缓冲液",
    "短时间:5L/min; 长时间:1L/min",
    ""
  ],
  "镁": [
    "GBZ/T300.16—2017",
    "样品在室温下可长期保存",
    "微孔滤膜 | 酸消解",
    "短时间:5L/min",
    ""
  ],
  "三溴甲烷": [
    "GBZ/T300.161—2018",
    "样品在室温下可保存7d",
    "活性炭管，溶剂解吸型 | 解吸液:二硫化碳",
    "短时间:0.2L/min; 长时间:0.05L/min; 个体:0.05L/min",
    "GBZ/T 300.161—2018 工作场所空气有毒物质测定 第 161 部分：三溴甲烷/4.三溴甲烷的溶剂解吸-气相色谱法"
  ],
  "苯醌": [
    "GBZ/T300.162—2018",
    "样品在室温下可保存14d",
    "硅胶管，溶剂解吸型 | 解吸液:乙腈",
    "短时间:0.2L/min; 长时间:0.05L/min; 个体:0.05L/min",
    ""
  ],
  "乙草胺": [
    "GBZ/T300.165—2024",
    "样品在室温（25℃）可保存30d",
    "硅胶管，溶剂解吸型 | 解吸液:甲醇",
    "短时间:2L/min; 长时间:1L/min",
    ""
  ],
  "2-氨基吡啶": [
    "GBZ/T300.166—2025",
    "样品在室温下可保存14d",
    "硫酸浸渍玻璃纤维滤膜 | 洗脱液:硫酸溶液",
    "短时间:3L/min; 长时间:1L/min",
    ""
  ],
  "锰": [
    "GBZ/T300.17—2017",
    "样品在室温下可长期保存",
    "微孔滤膜 | 酸消解",
    "短时间:5L/min; 长时间:1L/min",
    ""
  ],
  "氯化汞": [
    "GBZ/T300.18—2017",
    "样品24 h内测定；样品应在24 h内测定",
    "大型气泡吸收管 | 吸收液:酸性高锰酸钾",
    "短时间:0.5L/min",
    "GBZ/T 300.18—2017工作场所空气有毒物质测定第18部分：汞及其化合物/4.氯化汞的溶液吸收-原子荧光光谱法"
  ],
  "汞": [
    "GBZ/T300.18—2017",
    "样品24 h内测定；样品应在24 h内测定",
    "大型气泡吸收管 | 吸收液:酸性高锰酸钾",
    "短时间:0.5L/min",
    ""
  ],
  "钼": [
    "GBZ/T300.19—2017",
    "样品在室温下可长期保存",
    "微孔滤膜 | 酸消解",
    "短时间:5L/min; 长时间:1L/min",
    ""
  ],
  "锑": [
    "GBZ/T300.2—2017",
    "样品在室温下可长期保存",
    "微孔滤膜 | 酸消解",
    "短时间:5L/min; 长时间:1L/min",
    ""
  ],
  "氢氧化钾": [
    "GBZ/T300.21—2017",
    "样品在室温下可长期保存",
    "微孔滤膜 | 洗脱液:水",
    "短时间:5L/min; 长时间:1L/min",
    "GBZ/T 300.21—2017工作场所空气有毒物质测定 第 21 部分：钾及其化合物/4.钾及其化合物的溶剂洗脱-火焰原子吸收光谱法"
  ],
  "钾": [
    "GBZ/T300.21—2017",
    "样品在室温下可长期保存",
    "微孔滤膜 | 洗脱液:水",
    "短时间:5L/min; 长时间:1L/min",
    ""
  ],
  "氢氧化钠": [
    "GBZ/T300.22—2017",
    "样品在室温下可长期保存",
    "微孔滤膜 | 显色剂:碳酸钠",
    "短时间:5L/min",
    "GBZ/T 300.22—2017 工作场所空气有毒物质测定 第 22 部分：钠及其化合物/4.钠及其化合的溶剂洗脱-火焰原子吸收光谱法"
  ],
  "碳酸钠": [
    "GBZ/T300.22—2017",
    "样品在室温下可长期保存",
    "微孔滤膜 | 显色剂:碳酸钠",
    "短时间:5L/min",
    "GBZ/T 300.22—2017 工作场所空气有毒物质测定 第22部分：钠及其化合物/4.钠及其化合物的溶剂洗脱-火焰原子吸收光谱法"
  ],
  "钠": [
    "GBZ/T300.22—2017",
    "样品在室温下可长期保存",
    "微孔滤膜 | 显色剂:碳酸钠",
    "短时间:5L/min",
    ""
  ],
  "锶": [
    "GBZ/T300.23—2017",
    "样品在室温下可长期保存",
    "微孔滤膜 | 酸消解",
    "短时间:5L/min; 长时间:1L/min",
    ""
  ],
  "钽": [
    "GBZ/T300.24—2017",
    "应尽快测",
    "微孔滤膜 | 干灰化",
    "短时间:5L/min; 长时间:1L/min",
    ""
  ],
  "铊": [
    "GBZ/T300.25—2017",
    "样品在室温下可保存15d",
    "微孔滤膜 | 酸洗脱",
    "短时间:5L/min; 长时间:1L/min",
    ""
  ],
  "二氧化锡": [
    "GBZ/T300.26—2017",
    "样品在室温下可长期保存",
    "微孔滤膜 | 显色剂:栎精",
    "短时间:5L/min; 长时间:1L/min",
    "GBZ/T 300.26—2017 工作场所空气有毒物质测定 第26部分：锡及其无机化合物/3.锡及其无机化合物的酸消解-火焰原子吸收光谱法|GBZ/T 300.26—2017 工作场所空气有毒物质测定 第26部分：锡及其无机化合物/4.二氧化锡的栎精分光光度法"
  ],
  "锡": [
    "GBZ/T300.26—2017",
    "样品在室温下可长期保存",
    "微孔滤膜 | 酸消解",
    "短时间:5L/min",
    ""
  ],
  "三乙基氯化锡": [
    "GBZ/T300.27—2017",
    "样品在常温下可保存3d，在4℃下可保存7d，在-18℃下可保存14d",
    "多孔玻板吸收管 | 解吸液:甲醇",
    "短时间:1L/min; 长时间:0.2L/min",
    ""
  ],
  "三甲基氯化锡": [
    "GBZ/T300.27—2017",
    "样品在常温下可保存7d，在4 ℃下可保存14d",
    "多孔玻板吸收管 | 解吸液:乙酸-乙腈",
    "短时间:1L/min; 长时间:0.25L/min",
    ""
  ],
  "二月桂酸二丁基锡": [
    "GBZ/T300.27—2017",
    "样品应尽快测定",
    "多孔玻板吸收管 | 显色剂:双硫腙",
    "短时间:1L/min",
    ""
  ],
  "钨": [
    "GBZ/T300.28—2017",
    "样品在室温下可长期保存",
    "微孔滤膜 | 酸消解",
    "短时间:5L/min; 长时间:1L/min",
    ""
  ],
  "钒": [
    "GBZ/T300.29—2017",
    "样品在室温下可长期保存",
    "微孔滤膜 | 酸消解",
    "短时间:5L/min; 长时间:1L/min",
    ""
  ],
  "钇": [
    "GBZ/T300.30—2017",
    "样品在常温下可长期保存",
    "微孔滤膜 | 酸消解",
    "短时间:5L/min; 长时间:1L/min",
    ""
  ],
  "钡": [
    "GBZ/T300.3—2017",
    "样品在室温下可长期保存",
    "微孔滤膜 | 酸消解",
    "短时间:5L/min; 长时间:1L/min",
    ""
  ],
  "氧化锌": [
    "GBZ/T300.31—2017",
    "样品在室温下可长期保存",
    "微孔滤膜 | 酸消解",
    "短时间:5L/min; 长时间:1L/min",
    "GBZ/T 300.31—2017 工作场所空气有毒物质测定 第31部分：锌及其化合物/4.锌及其化合物的酸消解-火焰原子吸收光谱法"
  ],
  "氯化锌烟": [
    "GBZ/T300.31—2017",
    "样品在室温下可长期保存",
    "微孔滤膜 | 酸消解",
    "短时间:5L/min; 长时间:1L/min",
    "GBZ/T 300.31—2017 工作场所空气有毒物质测定 第31部分：锌及其化合物/4.锌及其化合物的酸消解-火焰原子吸收光谱法"
  ],
  "锌": [
    "GBZ/T300.31—2017",
    "样品在室温下可长期保存",
    "微孔滤膜 | 酸消解",
    "短时间:5L/min; 长时间:1L/min",
    ""
  ],
  "锆": [
    "GBZ/T300.32—2017",
    "样品在室温下可长期保存",
    "微孔滤膜 | 显色剂:二甲酚橙",
    "短时间:5L/min; 长时间:1L/min",
    ""
  ],
  "金属": [
    "GBZ/T300.33—2017",
    "在常温下可保存7d",
    "微孔滤膜 | 酸消解",
    "短时间:5L/min; 长时间:1L/min",
    ""
  ],
  "稀土金属": [
    "GBZ/T300.34—2017",
    "样品在室温下可保存7d",
    "微孔滤膜",
    "短时间:5L/min; 长时间:1L/min",
    ""
  ],
  "三氟化硼": [
    "GBZ/T300.35—2017",
    "样品在室温下可保存3 d",
    "多孔玻板吸收管 | 吸收液:氢氧化钠溶液",
    "短时间:1L/min",
    ""
  ],
  "一氧化碳": [
    "GBZ/T300.37—2017",
    "样品在24 h内测定",
    "采气袋 | 不分光红外线",
    "采气袋法，无泵流量",
    "GBZ/T 300.37—2017工作场所空气有毒物质测定第37部分：一氧化碳和二氧化碳/4.一氧化碳的不分光红外线气体分析仪法"
  ],
  "二氧化碳": [
    "GBZ/T300.37—2017",
    "样品在24 h内测定",
    "采气袋 | 不分光红外线",
    "采气袋法，无泵流量",
    "GBZ/T 300.37—2017工作场所空气有毒物质测定第37部分：一氧化碳和二氧化碳/4.二氧化碳的不分光红外线气体分析仪法"
  ],
  "二硫化碳": [
    "GBZ/T300.38—2017",
    "样品在冰箱内可保存7 d",
    "活性炭管，溶剂解吸型 | 解吸液:苯",
    "短时间:0.2L/min; 长时间:0.05L/min",
    "GBZ/T 300.38—2017 工作场所空气有毒物质测定 第100部分：二硫化碳/4.二硫化碳的溶剂解吸-气相色谱法|GBZ/T 300.38—2017 工作场所空气有毒物质测定 第100部分：二硫化碳/5.二硫化碳的溶剂解吸-二乙胺分光光度法"
  ],
  "铍": [
    "GBZ/T300.4—2017",
    "样品在室温下可长期保存",
    "微孔滤膜 | 酸消解",
    "短时间:5L/min; 长时间:1L/min",
    ""
  ],
  "叠氮化钠": [
    "GBZ/T300.43—2017",
    "样品一起运输、保存和测定",
    "多孔玻板吸收管 | 吸收液:氢氧化钾溶液",
    "短时间:1L/min",
    ""
  ],
  "叠氮酸": [
    "GBZ/T300.43—2017",
    "样品一起运输、保存和测定",
    "多孔玻板吸收管 | 吸收液:氢氧化钾溶液",
    "短时间:1L/min",
    ""
  ],
  "五氧化二磷": [
    "GBZ/T300.45—2017",
    "样品24h内测定",
    "多孔玻板吸收管 | 显色剂:钼酸铵",
    "短时间:1L/min",
    "GBZ/T 300.45—2017 工作场所空气有毒物质测定 第45部分：五氧化二磷和五硫化二磷/4.五氧化二磷的溶液吸收-钼酸铵分光光度法"
  ],
  "五硫化二磷": [
    "GBZ/T300.45—2017",
    "样品在室温下可保存2d",
    "多孔玻板吸收管 | 显色剂:对氨基二甲基苯胺",
    "短时间:0.5L/min",
    "GBZ/T 300.45—2017 工作场所空气有毒物质测定 第 45 部分：五氧化二磷的和五硫化二磷/5.五硫化二磷的溶液吸收-对氨基二甲基苯胺分光光度法"
  ],
  "三氯化磷": [
    "GBZ/T300.46—2017",
    "样品在室温下可保存2d",
    "多孔玻板吸收管 | 显色剂:钼酸铵",
    "短时间:0.5L/min",
    ""
  ],
  "三氯硫磷": [
    "GBZ/T300.46—2017",
    "样品在室温下可保存2d",
    "多孔玻板吸收管 | 显色剂:对氨基二甲基苯胺",
    "短时间:0.5L/min",
    ""
  ],
  "氧化砷": [
    "GBZ/T300.47—2017",
    "样品在低温下可保存15 d",
    "浸渍微孔滤膜 | 酸洗脱",
    "短时间:3L/min; 长时间:1L/min",
    ""
  ],
  "砷": [
    "GBZ/T300.47—2017",
    "样品在低温下可保存15 d",
    "微孔滤膜 | 酸消解",
    "短时间:3L/min; 长时间:1L/min",
    ""
  ],
  "砷化氢": [
    "GBZ/T300.47—2017",
    "样品应在24 h内测定",
    "多孔玻板吸收管 | 吸收液:次溴酸钠溶液",
    "短时间:1L/min",
    ""
  ],
  "臭氧": [
    "GBZ/T300.48—2017",
    "样品应在24h内测定",
    "大型气泡吸收管 | 显色剂:丁子香酚",
    "短时间:2L/min",
    "GBZ/T 300.48—2017工作场所空气有毒物质测定  第48部分： 臭氧和过氧化氢/4.臭氧的溶液吸收-丁子香酚分光光度法"
  ],
  "过氧化氢": [
    "GBZ/T300.48—2017",
    "样品应在24 h内测定",
    "多孔玻板吸收管 | 显色剂:硫酸氧钛",
    "短时间:1L/min",
    "GBZ/T 300.48—2017工作场所空气有毒物质测定第48部分：臭 氧和过氧化氢/5.过氧化氢的溶液吸收-硫酸氧钛分光光度法"
  ],
  "碲化铋": [
    "GBZ/T300.5—2017",
    "样品在室温下可保存7 d",
    "微孔滤膜 | 酸消解",
    "短时间:5L/min; 长时间:1L/min",
    ""
  ],
  "铋": [
    "GBZ/T300.5—2017",
    "样品在室温下可保存7d",
    "微孔滤膜 | 酸消解",
    "短时间:5L/min; 长时间:1L/min",
    ""
  ],
  "六氟化硫": [
    "GBZ/T300.51—2017",
    "样品24 h内测定",
    "采气袋 | 直接进样",
    "采气袋法，无泵流量",
    ""
  ],
  "氯化亚砜": [
    "GBZ/T300.52—2017",
    "样品在24 h内测定",
    "多孔玻板吸收管 | 显色剂:硫氰酸汞",
    "短时间:0.5L/min",
    ""
  ],
  "硒": [
    "GBZ/T300.53—2017",
    "样品在室温下可长期保存",
    "微孔滤膜 | 酸消解",
    "短时间:3L/min; 长时间:1L/min",
    ""
  ],
  "硒化氢": [
    "GBZ/T300.53—2017",
    "样品应在24h内测定",
    "多孔玻板吸收管 | 吸收液:氢氧化钠溶液",
    "短时间:0.5L/min",
    ""
  ],
  "碲": [
    "GBZ/T300.54—2017",
    "在室温下可保存7d",
    "微孔滤膜 | 酸消解",
    "短时间:2L/min; 长时间:1L/min",
    ""
  ],
  "碘": [
    "GBZ/T300.58—2017",
    "样品在室温下可以保存7 d",
    "活性炭管，溶剂解吸型",
    "短时间:0.5L/min",
    ""
  ],
  "壬烷": [
    "GBZ/T300.60—2017",
    "样品在室温下可保存7d，置4℃冰箱内可保存更长时间",
    "活性炭管，溶剂解吸型 | 解吸液:二硫化碳",
    "短时间:0.1L/min; 长时间:0.05L/min",
    "GBZ/T 300.60—2017 工作场所空气有毒物质测定 第 60 部分：戊烷、己烷、庚烷、辛烷和壬烷/4.壬烷的溶剂解吸-气相色谱法"
  ],
  "己烷": [
    "GBZ/T300.60—2017",
    "样品在室温下可保存7d，置4℃冰箱内可保存更长时间",
    "活性炭管，溶剂解吸型 | 解吸液:二硫化碳",
    "短时间:0.1L/min; 长时间:0.05L/min",
    ""
  ],
  "庚烷": [
    "GBZ/T300.60—2017",
    "样品在室温下可保存7d，置4℃冰箱内可保存更长时间",
    "活性炭管，溶剂解吸型 | 解吸液:二硫化碳",
    "短时间:0.1L/min; 长时间:0.05L/min",
    ""
  ],
  "戊烷": [
    "GBZ/T300.60—2017",
    "样品在室温下可保存7d，置4℃冰箱内可保存更长时间",
    "活性炭管，溶剂解吸型 | 解吸液:二硫化碳",
    "短时间:0.1L/min; 长时间:0.05L/min",
    "GBZ/T 300.60—2017工作场所空气有毒物质测定  第 60 部分：戊烷、己烷、庚烷、辛烷和壬烷/4.戊烷的溶剂解吸-气相色谱法|GBZ/T 300.60—2017工作场所空气有毒物质测定 第 60 部分：戊烷、己烷、庚烷、辛烷和壬烷/5.戊烷的热解吸-气相色谱法"
  ],
  "辛烷": [
    "GBZ/T300.60—2017",
    "样品在室温下可保存7d，置4℃冰箱内可保存更长时间",
    "活性炭管，溶剂解吸型 | 解吸液:二硫化碳",
    "短时间:0.1L/min; 长时间:0.05L/min",
    "GBZ/T 300.60—2017工作场所空气有毒物质测定  第 60 部分：戊烷、己烷、庚烷、辛烷和壬烷/4.辛烷的溶剂解吸-气相色谱法"
  ],
  "镉": [
    "GBZ/T300.6—2017",
    "样品在室温下可长期保存",
    "微孔滤膜 | 酸消解",
    "短时间:5L/min; 长时间:1L/min",
    ""
  ],
  "3-丁二烯": [
    "GBZ/T300.61—2017",
    "样品在4℃冰箱内可保存7 d",
    "活性炭管，溶剂解吸型 | 解吸液:二硫化碳",
    "短时间:0.2L/min; 长时间:0.03L/min",
    ""
  ],
  "丁烯": [
    "GBZ/T300.61—2017",
    "样品宜在24 h内测定",
    "采气袋 | 直接进样",
    "采气袋法，无泵流量",
    "GBZ/T 300.61—2017 工作场所空气有毒物质测定 第61部分：丁烯、1,3-丁二烯和二聚环戊二烯/4.丁烯的直接进样-气相色谱法"
  ],
  "二聚环戊二烯": [
    "GBZ/T300.61—2017",
    "样品在常温下可保存7 d",
    "活性炭管，溶剂解吸型 | 解吸液:二硫化碳",
    "短时间:0.2L/min; 长时间:0.03L/min",
    ""
  ],
  "抽余油": [
    "GBZ/T300.62—2017",
    "样品在冰箱内可保存7 d",
    "活性炭管，热解吸型 | 热解吸",
    "短时间:0.2L/min; 长时间:0.05L/min",
    "GBZ/T 300.62—2017工作场所空气有毒物质测定第62部分：溶剂汽油、液化石油气、抽余油(60°C~220°C)和松节油/6.抽余油的热解吸－气相色谱法"
  ],
  "松节油": [
    "GBZ/T300.62—2017",
    "样品在室温下可保存8 d",
    "活性炭管，溶剂解吸型 | 解吸液:二硫化碳",
    "短时间:0.1L/min; 长时间:0.05L/min",
    "GBZ/T 300.62—2017 工作场所空气有毒物质测定 第 62 部分：溶剂汽油、液化石油气、抽余油和松节油/7.松节油的溶剂解吸-气相色谱法"
  ],
  "液化石油气": [
    "GBZ/T300.62—2017",
    "样品应在24 h内测定",
    "采气袋 | 直接进样",
    "采气袋法，无泵流量",
    "GBZ/T 300.62—2017 工作场所空气有毒物质测定 第62部分：溶剂汽油、液化石油气、抽余油和松节油/5.液化石油气的直接进样-气相色谱法"
  ],
  "溶剂汽油": [
    "GBZ/T300.62—2017",
    "样品在室温下可保存7d",
    "活性炭管，热解吸型 | 热解吸",
    "短时间:0.1L/min; 长时间:0.05L/min",
    "GBZ/T 300.62—2017 工作场所空气有毒物质测定 第62部分：溶剂汽油、液化石油气、抽余油和松节油/4.溶剂汽油的热解吸-气相色谱法"
  ],
  "石蜡烟": [
    "GBZ/T300.64—2017",
    "样品在室温下可保存7d",
    "丙纶滤膜 | 称量法",
    "短时间:25L/min; 长时间:2L/min",
    "GBZ/T 300.64—2017 工作场所空气有毒物质测定 第 64 部分：石蜡烟/4.石蜡烟的溶剂洗脱-称量法"
  ],
  "环己烷": [
    "GBZ/T300.65—2017",
    "样品在室温下可保存8d",
    "活性炭管，溶剂解吸型 | 解吸液:二硫化碳",
    "短时间:0.1L/min; 长时间:0.05L/min",
    "GBZ/T 300.65—2017工作场所空气有毒物质测定 第65部分：环己烷和甲基环己烷/4.环己烷溶剂解吸-气相色谱法|GBZ/T 300.65—2017工作场所空气有毒物质测定 第65部分：环己烷和甲基环己烷/5.环己烷热解吸-气相色谱法"
  ],
  "甲基环己烷": [
    "GBZ/T300.65—2017",
    "样品在室温下可保存8d",
    "活性炭管，溶剂解吸型 | 解吸液:二硫化碳",
    "短时间:0.1L/min; 长时间:0.05L/min",
    ""
  ],
  "乙苯": [
    "GBZ/T300.66—2017",
    "样品在室温下可保存7d，置4℃冰箱内可保存14d",
    "活性炭管，溶剂解吸型 | 解吸液:二硫化碳",
    "短时间:0.1L/min; 长时间:0.05L/min",
    "GBZ/T 300.66—2017工作场所空气有毒物质测定 第 66 部分：苯、甲苯、二甲苯和乙苯/5.乙苯的溶剂解吸-气相色谱法GBZ/T 300.66—2017工作场所空气有毒物质测定 第 66 部分：苯、甲苯、二甲苯和乙苯/6.乙苯的热解吸-气相色谱法"
  ],
  "二甲苯": [
    "GBZ/T300.66—2017",
    "样品在室温下可保存7d，置4℃冰箱内可保存14d",
    "活性炭管，溶剂解吸型 | 解吸液:二硫化碳",
    "短时间:0.1L/min; 长时间:0.05L/min",
    "GBZ/T 300.66—2017工作场所空气有毒物质测定 第66部分：苯、甲苯、二甲苯和乙苯/4.二甲苯的无泵型采样-气相色谱法|GBZ/T 300.66—2017工作场所空气有毒物质测定 第66部分：苯、甲苯、二甲苯和乙苯/5.二甲苯的溶剂解吸-气相色谱法|GBZ/T 300.66—2017工作场所空气有毒物质测定 第66部分：苯、甲苯、二甲苯和乙苯/6.二甲苯的热解吸-气相色谱法"
  ],
  "甲苯": [
    "GBZ/T300.66—2017",
    "样品在室温下可保存7d，置4℃冰箱内可保存14d",
    "活性炭管，溶剂解吸型 | 解吸液:二硫化碳",
    "短时间:0.1L/min; 长时间:0.05L/min",
    "GBZ/T 300.66—2017工作场所空气有毒物质测定 第66部分：苯、甲苯、二甲苯和乙苯/4.甲苯的无泵型采样-气相色谱法|GBZ/T 300.66—2017工作场所空气有毒物质测定 第66部分：苯、甲苯、二甲苯和乙苯/5.甲苯的溶剂解吸-气相色谱法|GBZ/T 300.66—2017工作场所空气有毒物质测定 第66部分：苯、甲苯、二甲苯和乙苯/6.甲苯的热解吸-气相色谱法"
  ],
  "苯": [
    "GBZ/T300.66—2017",
    "样品在室温下可保存7d，置4℃冰箱内可保存14d",
    "活性炭管，溶剂解吸型 | 解吸液:二硫化碳",
    "短时间:0.1L/min; 长时间:0.05L/min",
    "GBZ/T 300.66—2017工作场所空气有毒物质测定第66部分：苯、甲苯、二甲苯和乙苯/4.苯的无泵型采样－气相色谱法|GBZ/T 300.66—2017工作场所空气有毒物质测定第66部分：苯、甲苯、二甲苯和乙苯/5.苯、甲苯、二甲苯和乙苯的溶剂解吸-气相色谱法|GBZ/T 300.66—2017工作场所空气有毒物质测定第66部分：苯、甲苯、二甲苯和乙苯/6.苯的热解吸－气相色谱法"
  ],
  "二乙烯基苯": [
    "GBZ/T300.68—2017",
    "样品在室温下可保存7d",
    "活性炭管，溶剂解吸型 | 解吸液:二硫化碳",
    "短时间:0.2L/min; 长时间:0.05L/min",
    ""
  ],
  "甲基苯乙烯": [
    "GBZ/T300.68—2017",
    "样品置冰箱内可保存14d",
    "活性炭管，溶剂解吸型 | 解吸液:二硫化碳",
    "短时间:0.1L/min; 长时间:0.05L/min",
    ""
  ],
  "苯乙烯": [
    "GBZ/T300.68—2017",
    "样品置冰箱内可保存14d",
    "活性炭管，溶剂解吸型 | 解吸液:二硫化碳",
    "短时间:0.1L/min; 长时间:0.05L/min",
    "GBZ/T300.68—2017工作场所空气有毒物质测定第68部分：苯乙烯、甲基苯乙烯和二乙烯基苯/4.苯乙烯的溶剂解吸一气相色谱法|GBZ/T300.68—2017工作场所空气有毒物质测定第68部分：苯乙烯、甲基苯乙烯和二乙烯基苯/5.苯乙烯的热解吸-气相色谱法"
  ],
  "氢化三联苯": [
    "GBZ/T300.69—2017",
    "样品在常温下可保存7d",
    "活性炭管，溶剂解吸型 | 解吸液:二硫化碳",
    "短时间:0.3L/min; 长时间:0.05L/min",
    ""
  ],
  "联苯": [
    "GBZ/T300.69—2017",
    "样品在室温下可保存5d",
    "活性炭管，溶剂解吸型 | 解吸液:二硫化碳",
    "短时间:0.2L/min; 长时间:0.05L/min",
    ""
  ],
  "氧化钙": [
    "GBZ/T300.7—2017",
    "样品在室温下可长期保存",
    "微孔滤膜 | 酸消解",
    "短时间:5L/min; 长时间:1L/min",
    "GBZ/T 300.7—2017 工作场所空气有毒物质测定 第7部分：钙及其化合物/4.钙及其化合物的酸消解-火焰原子吸收光谱法"
  ],
  "氰氨化钙": [
    "GBZ/T300.7—2017",
    "样品在室温下可保存7d",
    "超细玻璃纤维滤纸 | 洗脱液:盐酸溶液",
    "短时间:4L/min; 长时间:2L/min",
    "GBZ/T 300.7—2017 工作场所空气有毒物质测定 第 7 部分：钙及其化合物/4.钙及其化合物的酸消解-火焰原子吸收光谱法"
  ],
  "钙": [
    "GBZ/T300.7—2017",
    "样品在室温下可保存7d",
    "微孔滤膜 | 酸消解",
    "短时间:5L/min; 长时间:1L/min",
    ""
  ],
  "三氯甲烷": [
    "GBZ/T300.73—2017",
    "样品在室温下可保存7d",
    "活性炭管，溶剂解吸型 | 解吸液:二硫化碳",
    "短时间:0.1L/min; 长时间:0.05L/min",
    "GBZ/T 300.73—2017工作场所空气有毒物质测定第73部分：氯甲烷、二氯甲烷、三氯甲烷和四氯化碳/5.三氯甲烷的溶剂解吸-气相色谱法"
  ],
  "二氯甲烷": [
    "GBZ/T300.73—2017",
    "样品宜尽快测定",
    "采气袋 | 直接进样",
    "采气袋法，无泵流量",
    "GBZ/T 300.73—2017 工作场所空气有毒物质测定第73部分：氯甲烷、二氯甲烷、三氯甲烷和四氯化碳/4.二氯甲烷的直接进样-气相色谱法"
  ],
  "四氯化碳": [
    "GBZ/T300.73—2017",
    "样品在室温下可保存7d",
    "活性炭管，溶剂解吸型 | 解吸液:二硫化碳",
    "短时间:0.1L/min; 长时间:0.05L/min",
    "GBZ/T 300.73—2017工作场所空气有毒物质测定 第 73 部分：氯甲烷、二氯甲烷、三氯甲烷和四氯化碳/5.四氯化碳的溶剂解吸-气相色谱法"
  ],
  "氯甲烷": [
    "GBZ/T300.73—2017",
    "样品宜尽快测定",
    "采气袋 | 直接进样",
    "采气袋法，无泵流量",
    ""
  ],
  "六氟丙烯": [
    "GBZ/T300.77—2017",
    "样品在室温下可保存7d",
    "活性炭管，热解吸型 | 热解吸",
    "短时间:0.2L/min; 长时间:0.05L/min",
    ""
  ],
  "四氟乙烯": [
    "GBZ/T300.77—2017",
    "样品在室温下可保存8h",
    "采气袋 | 直接进样",
    "采气袋法，无泵流量",
    ""
  ],
  "三氯乙烯": [
    "GBZ/T300.78—2017",
    "样品在室温下可保存10d",
    "活性炭管，热解吸型 | 热解吸",
    "短时间:0.1L/min; 长时间:0.05L/min",
    "GBZ/T 300.78—2017工作场所空气有毒物质测定  第78部分：氯乙烯、二氯乙烯、三氯乙烯和四氯乙烯/7.三氯乙烯的无泵型采样器-气相色谱法|GBZ/T 300.78—2017工作场所空气有毒物质测定  第78部分：氯乙烯、二氯乙烯、三氯乙烯和四氯乙烯/6.三氯乙烯的溶剂解吸-气相色谱法|GBZ/T 300.78—2017工作场所空气有毒物质测定  第78部分：氯乙烯、二氯乙烯、三氯乙烯和四氯乙烯/4.三氯乙烯的热解吸-气相色谱法"
  ],
  "二氯乙烯": [
    "GBZ/T300.78—2017",
    "样品在室温下可保存5d，冰箱内保存7d，-20℃保存14d",
    "活性炭管，热解吸型 | 热解吸",
    "短时间:0.1L/min; 长时间:0.05L/min",
    ""
  ],
  "四氯乙烯": [
    "GBZ/T300.78—2017",
    "样品在室温下可保存10d",
    "活性炭管，热解吸型 | 热解吸",
    "短时间:0.1L/min; 长时间:0.05L/min",
    "GBZ/T 300.78—2017工作场所空气有毒物质测定  第78部分：氯乙烯、二氯乙烯、三氯乙烯和四氯乙烯/4.四氯乙烯的热解吸-气相色谱法|GBZ/T 300.78—2017工作场所空气有毒物质测定  第78部分：氯乙烯、二氯乙烯、三氯乙烯和四氯乙烯/6.四氯乙烯的溶剂解吸-气相色谱法|GBZ/T 300.78—2017工作场所空气有毒物质测定  第78部分：氯乙烯、二氯乙烯、三氯乙烯和四氯乙烯/7.四氯乙烯的无泵型采样器-气相色谱法"
  ],
  "氯乙烯": [
    "GBZ/T300.78—2017",
    "样品在室温下可保存5d，冰箱内保存7d，-20℃保存14d",
    "活性炭管，热解吸型 | 热解吸",
    "短时间:0.1L/min; 长时间:0.05L/min",
    "GBZ/T 300.78—2017 工作场所空气有毒物质测定 第78部分：氯乙烯、二氯乙烯、三氯乙烯和四氯乙烯/4.氯乙烯的热解吸-气相色谱法|GDOHTQC 030—2024 工作场所空气有毒物质测定氯乙烯的溶剂解吸-气相色谱法"
  ],
  "二氯丙烯": [
    "GBZ/T300.80—2017",
    "样品在室温下可保存3d，4℃下可保存7d",
    "活性炭管，热解吸型 | 热解吸",
    "短时间:0.2L/min; 长时间:0.05L/min",
    ""
  ],
  "氯丙烯": [
    "GBZ/T300.80—2017",
    "样品在室温下可保存3d，4℃下可保存7d",
    "活性炭管，热解吸型 | 热解吸",
    "短时间:0.2L/min; 长时间:0.05L/min",
    "GBZ/T 300.80—2017 工作场所空气有毒物质测定 第80部分：氯丙烯和二氯丙烯/4.氯丙烯和二氯丙烯的热解吸-气相色谱法"
  ],
  "铯": [
    "GBZ/T300.8—2017",
    "样品在室温下可保存7d",
    "微孔滤膜 | 洗脱液:水",
    "短时间:5L/min; 长时间:1L/min",
    ""
  ],
  "三氯苯": [
    "GBZ/T300.81—2017",
    "样品在室温下可保存7d",
    "活性炭管，溶剂解吸型 | 解吸液:二硫化碳",
    "短时间:0.1L/min; 长时间:0.05L/min",
    ""
  ],
  "二氯苯": [
    "GBZ/T300.81—2017",
    "样品在室温下可保存7d",
    "活性炭管，溶剂解吸型 | 解吸液:二硫化碳",
    "短时间:0.1L/min; 长时间:0.05L/min",
    ""
  ],
  "对二氯苯": [
    "GBZ/T300.81—2017",
    "样品在室温下可保存7d",
    "活性炭管，溶剂解吸型 | 解吸液:二硫化碳",
    "短时间:0.1L/min; 长时间:0.05L/min",
    "GBZ/T 300.81—2017 工作场所空气有毒物质测定第81部分：氯苯、二氯苯和三氯苯/4.二氯苯的溶剂解吸-气相色谱法"
  ],
  "氯苯": [
    "GBZ/T300.81—2017",
    "样品在室温下可保存7d",
    "活性炭管，溶剂解吸型 | 解吸液:二硫化碳",
    "短时间:0.1L/min; 长时间:0.05L/min",
    "GBZ-T 300.81—2017 工作场所空气有毒物质测定 第81部分：氯苯、二氯苯和三氯苯/4 氯苯的溶剂解吸-气相色谱法"
  ],
  "邻二氯苯": [
    "GBZ/T300.81—2017",
    "样品在室温下可保存7d",
    "活性炭管，溶剂解吸型 | 解吸液:二硫化碳",
    "短时间:0.1L/min; 长时间:0.05L/min",
    "GBZ/T 300.81—2017 工作场所空气有毒物质测定 第81部分：氯苯、二氯苯和三氯苯/4.邻二氯苯的溶剂解吸-气相色谱法"
  ],
  "对氯甲苯": [
    "GBZ/T300.82—2017",
    "样品在室温下可保存7d",
    "活性炭管，溶剂解吸型 | 解吸液:二硫化碳",
    "短时间:0.1L/min; 长时间:0.05L/min",
    ""
  ],
  "苄基氯": [
    "GBZ/T300.82—2017",
    "样品在室温下可保存7d",
    "活性炭管，溶剂解吸型 | 解吸液:二硫化碳",
    "短时间:0.1L/min; 长时间:0.05L/min",
    ""
  ],
  "溴苯": [
    "GBZ/T300.83—2017",
    "样品在室温下可保存7d",
    "活性炭管，溶剂解吸型 | 解吸液:二硫化碳",
    "短时间:0.1L/min; 长时间:0.05L/min",
    ""
  ],
  "丙醇": [
    "GBZ/T300.84—2017",
    "样品在室温下可保存7d",
    "活性炭管，溶剂解吸型 | 解吸液:二硫化碳",
    "短时间:0.1L/min; 长时间:0.05L/min",
    ""
  ],
  "异丙醇": [
    "GBZ/T300.84—2017",
    "样品在室温下可保存7d",
    "活性炭管，溶剂解吸型 | 解吸液:二硫化碳",
    "短时间:0.1L/min; 长时间:0.05L/min",
    "GBZ/T 300.84—2017 工作场所空气有毒物质测定 第 84 部分：甲醇 、丙醇和辛醇/6.异丙醇的溶剂解吸-气相色谱法"
  ],
  "甲醇": [
    "GBZ/T300.84—2017",
    "样品在室温下可保存7d",
    "硅胶管，溶剂解吸型 | 解吸液:水",
    "短时间:0.1L/min; 长时间:0.05L/min",
    "GBZ/T 300.84—2017 工作场所空气有毒物质测定 第84部分：甲醇、丙醇和辛醇/4.甲醇的溶剂解吸-气相色谱法|GBZ/T 300.84—2017 工作场所空气有毒物质测定 第84部分：甲醇、丙醇和辛醇/5.甲醇的热吸-气相色谱法"
  ],
  "辛醇": [
    "GBZ/T300.84—2017",
    "样品在室温下可保存7d",
    "活性炭管，溶剂解吸型 | 解吸液:二硫化碳",
    "短时间:0.1L/min; 长时间:0.05L/min",
    ""
  ],
  "丁醇": [
    "GBZ/T300.85—2017",
    "样品在室温下可保存7d",
    "活性炭管，溶剂解吸型 | 解吸液:二硫化碳",
    "短时间:0.1L/min; 长时间:0.05L/min",
    ""
  ],
  "丙烯醇": [
    "GBZ/T300.85—2017",
    "样品在室温下宜尽快测定，在-20℃冰箱中可保存5d",
    "活性炭管，溶剂解吸型 | 解吸液:二氯甲烷",
    "短时间:0.1L/min; 长时间:0.05L/min",
    "GBZ/T 300.85—2017工作场所空气有毒物质测定第85部分：丁醇、戊醇和丙烯醇/5．丙烯醇的溶剂解吸﹣气相色谱法"
  ],
  "戊醇": [
    "GBZ/T300.85—2017",
    "样品在室温下可保存7d",
    "活性炭管，溶剂解吸型 | 解吸液:二硫化碳",
    "短时间:0.1L/min; 长时间:0.05L/min",
    "GBZ/T 300.85—2017工作场所空气有毒物质测定第85部分：丁醇 、戊醇和丙烯醇/4.戊醇的溶剂解吸-气相色谱法"
  ],
  "乙二醇": [
    "GBZ/T300.86—2017",
    "样品在室温下可保存14d",
    "硅胶管，溶剂解吸型 | 解吸液:甲醇",
    "短时间:0.1L/min; 长时间:0.05L/min",
    "GBZ/T 300.86—2017 工作场所空气有毒物质测定 第86部分：乙二醇/4.乙二醇的溶剂解吸-气相色谱法"
  ],
  "3-二氯丙醇": [
    "GBZ/T300.88—2017",
    "样品在室温下可保存5d",
    "硅胶管，溶剂解吸型 | 解吸液:乙醇",
    "短时间:0.1L/min",
    ""
  ],
  "氯乙醇": [
    "GBZ/T300.88—2017",
    "样品在室温下可保存7d",
    "活性炭管，溶剂解吸型 | 解吸液:二硫化碳",
    "短时间:0.1L/min",
    ""
  ],
  "三价铬": [
    "GBZ/T300.9—2017",
    "样品在室温下可保存3 d",
    "微孔滤膜 | 显色剂:二苯碳酰二肼",
    "短时间:3L/min; 长时间:1L/min",
    ""
  ],
  "六价铬": [
    "GBZ/T300.9—2017",
    "样品应在48 h内测定；样品在室温下可保存3 d",
    "冲击式吸收管 | 显色剂:二苯碳酰二肼",
    "短时间:3L/min",
    ""
  ],
  "铬": [
    "GBZ/T300.9—2017",
    "样品在室温下可保存3d",
    "微孔滤膜 | 酸消解",
    "短时间:5L/min; 长时间:1L/min",
    ""
  ],
  "五氯酚": [
    "GBZ/T300.93—2017",
    "样品在室温下可保存8d",
    "微孔滤膜 | 吸收液:乙二醇",
    "短时间:1L/min; 长时间:0.5L/min",
    ""
  ],
  "五氯酚钠": [
    "GBZ/T300.93—2017",
    "样品在室温下可保存8d",
    "微孔滤膜 | 吸收液:乙二醇",
    "短时间:1L/min; 长时间:0.5L/min",
    ""
  ],
  "1-甲氧基-2-丙醇": [
    "GBZ/T300.97—2017",
    "样品在室温下可保存7d",
    "活性炭管，溶剂解吸型 | 解吸液:二氯甲烷",
    "短时间:0.1L/min; 长时间:0.05L/min",
    ""
  ],
  "二丙二醇甲醚": [
    "GBZ/T300.97—2017",
    "样品在室温下可保存7d",
    "活性炭管，溶剂解吸型 | 解吸液:二氯甲烷",
    "短时间:0.1L/min; 长时间:0.05L/min",
    "GBZ/T 300.97—2017 工作场所空气有毒物质测定第97部分：二丙二醇甲醚和1-甲氧基-2-丙醇/4.二丙二醇甲醚的溶剂解吸-气相色谱法"
  ],
  "丁醛": [
    "GBZ/T300.99—2017",
    "样品在室温下可保存3d",
    "硅胶管，热解吸型 | 热解吸",
    "短时间:0.1L/min; 长时间:0.05L/min",
    ""
  ],
  "乙醛": [
    "GBZ/T300.99—2017",
    "样品在室温下可保存5d",
    "硅胶管，溶剂解吸型 | 解吸液:水",
    "短时间:0.1L/min; 长时间:0.05L/min",
    "GBZ/T 300.99—2017 工作场所空气有毒物质测定 第 99 部分：甲醛、乙醛和丁醛/5.乙醛的溶剂解吸-气相色谱法"
  ],
  "甲醛": [
    "GBZ/T300.99—2017",
    "样品在室温下可保存24h，在4℃冰箱内可保存3d",
    "大型气泡吸收管 | 显色剂:酚试剂",
    "短时间:0.2L/min",
    "GBZ/T 300.99—2017 工作场所空气有毒物质测定 第99部分：甲醛、乙醛和丁醛/4.甲醛的溶液吸收-酚试剂分光光度法"
  ],
  "照度": [
    "GB/T5700—2023",
    "/",
    "直读 | 直读",
    "直读",
    "GB/T 5700—2023照明测量方法"
  ],
  "非密封放射性物质放射防护检测": [
    "GB/T14056.1—2008",
    "/",
    "/",
    "/",
    "GB/T 14056.1—2008表面污染测定第1部分：β发射体(Eβmax>0.15MeV)和α发射体"
  ],
  "风量": [
    "GB/T16758—2008",
    "/",
    "直读 | 直读",
    "直读",
    "GB/T 16758—2008排风罩的分类及技术条件 附录A.2"
  ],
  "气压": [
    "GB/T18204.1—2013",
    "/",
    "直读 | 直读",
    "直读",
    "GB/T 18204.1—2013 公共场所卫生检验方法 第1部分：物理因素"
  ],
  "温度": [
    "GB/T18204.1—2013",
    "/",
    "直读 | 直读",
    "直读",
    "GB/T 18204.1—2013 公共场所卫生检验方法 第1部分：物理因素"
  ],
  "湿度": [
    "GB/T18204.1—2013",
    "/",
    "直读 | 直读",
    "直读",
    "GB/T 18204.1—2013 公共场所卫生检验方法 第1部分：物理因素"
  ],
  "风速": [
    "GB/T18204.1—2013",
    "/",
    "直读 | 直读",
    "直读",
    "GB/T 18204.1—2013 公共场所卫生检验方法 第1部分：物理因素"
  ],
  "一氧化氮": [
    "GBZ/T160.29—2004",
    "样品尽量在当天测定",
    "多孔玻板吸收管 | 显色剂:对氨基苯磺酸",
    "短时间:0.5L/min",
    ""
  ],
  "二氧化氮": [
    "GBZ/T160.29—2004",
    "样品尽量在当天测定",
    "多孔玻板吸收管 | 显色剂:对氨基苯磺酸",
    "短时间:0.5L/min",
    ""
  ],
  "氰化氢": [
    "GBZ/T160.29—2004",
    "样品尽量在当天测定",
    "多孔玻板吸收管 | 显色剂:异菸酸钠",
    "短时间:0.2L/min",
    "GBZ/T 160.29—2004 工作场所空气中有毒物质测定 无机含氮化合物/5.氰化氢的异菸酸钠-巴比妥酸钠分光光度法"
  ],
  "氰化物": [
    "GBZ/T160.29—2004",
    "在室温下至少可保存7d",
    "微孔滤膜 | 显色剂:异菸酸钠",
    "短时间:0.2L/min",
    "GBZ/T 160.29—2004 工作场所空气中有毒物质测定 无机含氮化合物/5.氰化物的异菸酸钠-巴比妥酸钠分光光度法"
  ],
  "氟化氢": [
    "GBZ/T160.36—2004",
    "在室温下至少可稳定7d",
    "多孔玻板吸收管 | 吸收液:碱性溶液",
    "短时间:1L/min",
    "GBZ/T 160.36—2004 工作场所空气有毒物质测定 氟化物/3.离子选择电极法"
  ],
  "甲酚": [
    "GBZ/T160.51—2007",
    "样品在室温下至少可保存10d",
    "硅胶管，溶剂解吸型 | 解吸液:丙酮",
    "短时间:0.3L/min; 长时间:0.05L/min",
    "GBZ/T 160.51—2007 工作场所空气有毒物质测定 酚类化合物/3.甲酚的溶剂解吸-气相色谱法"
  ],
  "甲乙酮": [
    "GBZ/T300.103—2017",
    "样品在室温下可保存7d",
    "活性炭管，溶剂解吸型 | 解吸液:二硫化碳",
    "短时间:0.1L/min; 长时间:0.05L/min",
    "GBZ/T 300.103—2017工作场所空气有毒物质测定第103部分：丙酮、丁酮和甲基异丁基甲酮/4.丙酮、丁酮和甲基异丁基甲酮的溶剂解吸-气相色谱法"
  ],
  "甲苯-2,4-二异氰酸酯": [
    "GBZ/T300.132—2017",
    "样品在室温下避光可保存5d；样品在2℃～8℃避光环境中可保存14 天",
    "冲击式吸收管 | 吸收液:酸溶液",
    "短时间:3L/min",
    "GBZ/T 300.132—2017 工作场所空气有毒物质测定 第132部分：甲苯二异氰酸酯、二苯基甲烷二异氰酸酯和异佛尔酮二异氰酸酯/4.甲苯二异氰酸酯溶液吸收-气相色谱法"
  ],
  "二硝基苯": [
    "GBZ/T300.146—2017",
    "样品在室温下可保存7d",
    "硅胶管，溶剂解吸型",
    "短时间:0.2L/min; 长时间:0.05L/min",
    "GBZ/T 300.146—2017工作场所空气有毒物质测定 第146部分：硝基苯、硝基甲苯和硝基氯苯/4.二硝基苯的气相色谱法"
  ],
  "汞-金属汞": [
    "GBZ/T300.18—2017",
    "样品24 h内测定；样品应在24 h内测定",
    "大型气泡吸收管 | 吸收液:酸性高锰酸钾",
    "短时间:0.5L/min",
    "GBZ/T 300.18—2017工作场所空气有毒物质测定 第18部分：汞及其化合物/4.汞的溶液吸收-原子荧光光谱法"
  ],
  "1,2-二氯乙烯": [
    "GBZ/T300.78—2017；GDOHTQC035—2024",
    "样品在室温下可保存3d，冰箱内保存7d，-20℃保存14d",
    "活性炭管，热解吸型 | 热解吸",
    "短时间:0.1L/min; 长时间:0.05L/min",
    "GBZ/T 300.78—2017 工作场所空气有毒物质测定 第78部分：氯乙烯、二氯乙烯、三氯乙烯和四氯乙烯/5.1,2-二氯乙烯的溶剂解吸-气相色谱法|GDOHTQC 035—2024工作场所空气中二甲氧基甲烷的溶剂解吸-气相色谱法"
  ],
  "氢化锂": [
    "GBZ/T160.11—2004",
    "样品在室温下至少可保存7d",
    "微孔滤膜",
    "短时间:5L/min; 长时间:1L/min; 个体:1L/min",
    ""
  ],
  "氧化镍": [
    "GBZ/T160.16—2004",
    "样品在室温下可长期保存",
    "微孔滤膜",
    "短时间:5L/min; 长时间:1L/min; 个体:1L/min",
    ""
  ],
  "硝酸镍": [
    "GBZ/T160.16—2004",
    "样品在室温下可长期保存",
    "微孔滤膜",
    "短时间:5L/min; 长时间:1L/min; 个体:1L/min",
    ""
  ],
  "氢氰酸": [
    "GBZ/T160.29—2004",
    "样品尽量在当天测定",
    "多孔玻板吸收管 | 显色剂:对氨基苯磺酸",
    "短时间:0.5L/min",
    ""
  ],
  "黄磷": [
    "GBZ/T160.30—2004",
    "样品应尽快测定",
    "多孔玻板吸收管 | 直接进样",
    "短时间:1L/min",
    ""
  ],
  "三氯氧磷": [
    "GBZ/T160.30—2004",
    "标准未规定",
    "多孔玻板吸收管 | 直接进样",
    "短时间:1L/min",
    ""
  ],
  "硫酰氟": [
    "GBZ/T160.33—2004",
    "样品应当天尽快测定",
    "注射器 | 直接进样",
    "短时间:0.5L/min",
    ""
  ],
  "二氧化氯": [
    "GBZ/T160.37—2004",
    "样品应在48h内测定",
    "大型气泡吸收管 | 显色剂:酸性紫R",
    "短时间:0.1L/min",
    ""
  ],
  "萘烷": [
    "GBZ/T160.44—2004",
    "样品在室温下可保存5d",
    "活性炭管，溶剂解吸型 | 解吸液:二硫化碳",
    "短时间:0.2L/min; 长时间:0.05L/min; 个体:0.05L/min",
    ""
  ],
  "四氢化萘": [
    "GBZ/T160.44—2004",
    "样品在室温下可保存5d",
    "活性炭管，溶剂解吸型 | 解吸液:二硫化碳",
    "短时间:0.2L/min; 长时间:0.05L/min; 个体:0.05L/min",
    ""
  ],
  "蒽": [
    "GBZ/T160.44—2004",
    "样品在4℃冰箱内可保存7d",
    "玻璃纤维滤纸 | 洗脱液:溶剂洗脱",
    "短时间:0.2L/min; 长时间:0.05L/min; 个体:0.05L/min",
    ""
  ],
  "菲": [
    "GBZ/T160.44—2004",
    "样品在4℃冰箱内可保存7d",
    "玻璃纤维滤纸 | 洗脱液:溶剂洗脱",
    "短时间:25L/min; 长时间:1L/min; 个体:1L/min",
    ""
  ],
  "3,4-苯并(a)芘": [
    "GBZ/T160.44—2004",
    "样品在4℃冰箱内可保存7d",
    "玻璃纤维滤纸 | 洗脱液:溶剂洗脱",
    "短时间:25L/min; 长时间:1L/min; 个体:1L/min",
    ""
  ],
  "六氯乙烷": [
    "GBZ/T160.45—2007",
    "样品在室温下可保存7d",
    "活性炭管，溶剂解吸型 | 解吸液:二硫化碳",
    "短时间:0.3L/min; 长时间:0.05L/min; 个体:0.05L/min",
    ""
  ],
  "溴甲烷": [
    "GBZ/T160.45—2007",
    "样品应尽快测定",
    "注射器 | 直接进样",
    "短时间:0.3L/min; 长时间:0.05L/min; 个体:0.05L/min",
    ""
  ],
  "二氯二氟甲烷": [
    "GBZ/T160.45—2007",
    "样品室温下可保存7d",
    "活性炭管，溶剂解吸型 | 解吸液:二硫化碳",
    "短时间:0.2L/min; 长时间:0.05L/min; 个体:0.05L/min",
    ""
  ],
  "糠醇": [
    "GBZ/T160.48—2007",
    "样品在室温下可保存7d",
    "硅胶管，溶剂解吸型 | 解吸液:水",
    "短时间:0.5L/min; 长时间:0.05L/min",
    ""
  ],
  "异丁醇": [
    "GBZ/T160.48—2007",
    "样品在室温下可保存7d",
    "活性炭管，溶剂解吸型 | 解吸液:二硫化碳",
    "短时间:0.5L/min; 长时间:0.05L/min",
    ""
  ],
  "异戊醇": [
    "GBZ/T160.48—2007",
    "样品在室温下可保存7d",
    "活性炭管，溶剂解吸型 | 解吸液:二硫化碳",
    "短时间:0.5L/min; 长时间:0.05L/min",
    ""
  ],
  "异辛醇": [
    "GBZ/T160.48—2007",
    "样品在室温下可保存7d",
    "活性炭管，溶剂解吸型 | 解吸液:二硫化碳",
    "短时间:0.5L/min; 长时间:0.05L/min",
    ""
  ],
  "2-乙氧基乙醇": [
    "GBZ/T160.50—2004",
    "样品室温下至少可保存14d",
    "活性炭管，溶剂解吸型",
    "短时间:0.3L/min; 长时间:0.05L/min; 个体:0.05L/min",
    ""
  ],
  "beta-萘酚": [
    "GBZ/T160.51—2007",
    "样品在室温下可保存7d",
    "微孔滤膜 | 解吸液:丙酮",
    "短时间:0.3L/min; 长时间:0.05L/min; 个体:0.05L/min",
    ""
  ],
  "三硝基苯酚": [
    "GBZ/T160.51—2007",
    "样品在室温下可保存7d",
    "微孔滤膜 | 解吸液:丙酮",
    "短时间:5L/min; 长时间:1L/min; 个体:1L/min",
    ""
  ],
  "异丙醚": [
    "GBZ/T160.52—2007",
    "样品在室温下可保存7d",
    "活性炭管，热解吸型 | 热解吸",
    "短时间:0.1L/min; 长时间:0.05L/min; 个体:0.05L/min",
    ""
  ],
  "正丁基缩水甘油醚": [
    "GBZ/T160.52—2007",
    "样品于4℃冰箱中可保存10d",
    "活性炭管，溶剂解吸型 | 解吸液:二硫化碳",
    "短时间:0.2L/min; 长时间:0.03L/min; 个体:0.03L/min",
    ""
  ],
  "氨基苯甲醚": [
    "GBZ/T160.53—2004",
    "样品在室温下至少可保存7d",
    "活性炭管，溶剂解吸型 | 解吸液:二硫化碳",
    "短时间:0.2L/min; 长时间:0.05L/min; 个体:0.05L/min",
    ""
  ],
  "苯基醚": [
    "GBZ/T160.53—2004",
    "样品在室温下至少可保存5d",
    "活性炭管，溶剂解吸型 | 解吸液:二硫化碳",
    "短时间:0.2L/min; 长时间:0.05L/min; 个体:0.05L/min",
    ""
  ],
  "异丁醛": [
    "GBZ/T160.54—2007",
    "样品在室温下至少可保存3d",
    "硅胶管，热解吸型 | 热解吸",
    "短时间:0.1L/min; 长时间:0.05L/min; 个体:0.05L/min",
    ""
  ],
  "双乙烯酮": [
    "GBZ/T160.55—2007",
    "在15℃下至少可保存3d",
    "活性炭管，热解吸型 | 热解吸",
    "短时间:0.2L/min",
    ""
  ],
  "甲基环己酮": [
    "GBZ/T160.56—2004",
    "样品在室温下可保存7d",
    "活性炭管，溶剂解吸型 | 解吸液:二硫化碳",
    "短时间:0.3L/min; 长时间:0.05L/min; 个体:0.05L/min",
    ""
  ],
  "光气": [
    "GBZ/T160.61—2004",
    "当天测定完毕",
    "多孔玻板吸收管 | 显色剂:苯胺",
    "短时间:0.5L/min",
    ""
  ],
  "二甲基甲酰胺": [
    "GBZ/T160.62—2004",
    "样品在室温下可保存7d",
    "多孔玻板吸收管 | 解吸液:乙酸乙酯",
    "短时间:1L/min",
    ""
  ],
  "二甲基乙酰胺": [
    "GBZ/T160.62—2004",
    "样品在室温下可保存7d",
    "多孔玻板吸收管 | 解吸液:乙酸乙酯",
    "短时间:1L/min",
    ""
  ],
  "乙酸戊酯": [
    "GBZ/T160.63—2007",
    "样品在室温下至少可保存7d",
    "活性炭管，溶剂解吸型 | 解吸液:二硫化碳",
    "短时间:0.1L/min; 长时间:0.05L/min; 个体:0.05L/min",
    ""
  ],
  "乙酸异丁酯": [
    "GBZ/T160.63—2007",
    "样品在室温下至少可稳定30d",
    "活性炭管，溶剂解吸型 | 解吸液:二硫化碳",
    "短时间:0.1L/min; 长时间:0.05L/min; 个体:0.05L/min",
    ""
  ],
  "乙酸异戊酯": [
    "GBZ/T160.63—2007",
    "样品在室温下至少可稳定30d",
    "活性炭管，溶剂解吸型 | 解吸液:二硫化碳",
    "短时间:0.2L/min; 长时间:0.05L/min; 个体:0.05L/min",
    ""
  ],
  "1,4-丁内酯": [
    "GBZ/T160.63—2007",
    "样品在室温下至少可保存7d",
    "活性炭管，溶剂解吸型 | 解吸液:二硫化碳",
    "短时间:0.1L/min; 长时间:0.05L/min; 个体:0.05L/min",
    ""
  ],
  "丙烯酸乙酯": [
    "GBZ/T300.127—2017",
    "样品在室温下可保存7d",
    "活性炭管，溶剂解吸型 | 解吸液:二硫化碳",
    "短时间:0.1L/min; 长时间:0.05L/min",
    ""
  ],
  "丙烯酸丙酯": [
    "GBZ/T300.127—2017",
    "样品在室温下可保存7d",
    "活性炭管，溶剂解吸型 | 解吸液:二硫化碳",
    "短时间:0.1L/min; 长时间:0.05L/min",
    ""
  ],
  "丙烯酸戊酯": [
    "GBZ/T300.127—2017",
    "样品在室温下可保存7d",
    "活性炭管，溶剂解吸型 | 解吸液:二硫化碳",
    "短时间:0.1L/min; 长时间:0.05L/min",
    ""
  ],
  "甲基丙烯酸环氧丙酯": [
    "GBZ/T160.64—2004",
    "样品应在24h内测定",
    "大型气泡吸收管 | 直接进样",
    "短时间:0.1L/min; 长时间:0.05L/min",
    ""
  ],
  "N-甲基苯胺": [
    "GBZ/T160.72—2004",
    "样品在室温下至少可保存7d",
    "硅胶管，溶剂解吸型 | 显色剂:苯胺",
    "短时间:0.2L/min; 长时间:0.05L/min; 个体:0.05L/min",
    ""
  ],
  "N,N-二甲基苯胺": [
    "GBZ/T160.72—2004",
    "样品在室温下至少可保存7d",
    "硅胶管，溶剂解吸型 | 显色剂:苯胺",
    "短时间:0.2L/min; 长时间:0.05L/min; 个体:0.05L/min",
    ""
  ],
  "吡啶": [
    "GBZ/T160.75—2004",
    "样品在室温下可保存7d",
    "活性炭管，溶剂解吸型 | 解吸液:二硫化碳",
    "短时间:0.1L/min; 长时间:0.05L/min; 个体:0.05L/min",
    ""
  ],
  "呋喃": [
    "GBZ/T160.75—2004",
    "样品在室温下可保存7d",
    "活性炭管，热解吸型 | 热解吸",
    "短时间:0.1L/min; 长时间:0.05L/min; 个体:0.05L/min",
    ""
  ],
  "氢氧化铯": [
    "GBZ/T300.8—2017",
    "样品在室温下可保存7d",
    "微孔滤膜 | 洗脱液:水",
    "短时间:5L/min; 长时间:1L/min",
    ""
  ],
  "氧化镁": [
    "GBZ/T300.16—2017",
    "样品在室温下可长期保存",
    "微孔滤膜 | 酸消解",
    "短时间:5L/min",
    ""
  ],
  "氯化钾": [
    "GBZ/T300.21—2017",
    "样品在室温下可长期保存",
    "微孔滤膜 | 洗脱液:水",
    "短时间:5L/min; 长时间:1L/min",
    ""
  ],
  "五氧化二钒": [
    "GBZ/T300.29—2017",
    "样品在室温下可长期保存",
    "微孔滤膜 | 酸消解",
    "短时间:5L/min; 长时间:1L/min",
    ""
  ],
  "钒铁合金": [
    "GBZ/T300.29—2017",
    "样品在室温下可长期保存",
    "微孔滤膜 | 酸消解",
    "短时间:5L/min; 长时间:1L/min",
    ""
  ],
  "三氧化二砷": [
    "GBZ/T300.47—2017",
    "样品在低温下可保存15 d",
    "浸渍微孔滤膜 | 酸消解",
    "短时间:3L/min; 长时间:1L/min",
    ""
  ],
  "五氧化二砷": [
    "GBZ/T300.47—2017",
    "样品在低温下可保存15 d",
    "浸渍微孔滤膜 | 酸消解",
    "短时间:3L/min; 长时间:1L/min",
    ""
  ],
  "二氧化硒": [
    "GBZ/T300.53—2017",
    "样品在室温下可长期保存",
    "微孔滤膜 | 酸消解",
    "短时间:3L/min; 长时间:1L/min",
    ""
  ],
  "其他粉尘": [
    "GBZ/T192.1—2025",
    "长期",
    "丙纶滤膜",
    "短时间:15L/min~40L/min; 长时间:1L/min~5L/min",
    ""
  ],
  "砂轮磨尘": [
    "GBZ/T192.1—2025",
    "长期",
    "丙纶滤膜",
    "短时间:15L/min~40L/min; 长时间:1L/min~5L/min",
    ""
  ],
  "正己烷": [
    "GBZ/T300.60—2017",
    "样品在室温下可保存7d，置4℃冰箱内可保存更长时间",
    "活性炭管，溶剂解吸型 | 解吸液:二硫化碳",
    "短时间:0.1L/min; 长时间:0.05L/min",
    "GBZ/T 300.60—2017 工作场所空气有毒物质测定 第 60 部分：戊烷、己烷、庚烷、辛烷和壬烷/4.正己烷的溶剂解吸-气相色谱法 |GBZ/T 300.60—2017 工作场所空气有毒物质测定 第 60 部分：戊烷、己烷、庚烷、辛烷和壬烷/5.正己烷的热解吸-气相色谱法"
  ],
  "正庚烷": [
    "GBZ/T300.60—2017",
    "样品在室温下可保存7d，置4℃冰箱内可保存更长时间",
    "活性炭管，溶剂解吸型 | 解吸液:二硫化碳",
    "短时间:0.1L/min; 长时间:0.05L/min",
    "GBZ/T 300.60—2017 工作场所空气有毒物质测定 第60部分：戊烷、己烷、庚烷、辛烷和壬烷/4.正庚烷的溶剂解吸-气相色谱法 |GBZ/T 300.60—2017 工作场所空气有毒物质测定 第 60 部分：戊烷、己烷、庚烷、辛烷和壬烷/5.正庚烷的热解吸-气相色谱法"
  ],
  "正戊烷": [
    "GBZ/T300.60—2017",
    "样品在室温下可保存7d，置4℃冰箱内可保存更长时间",
    "活性炭管，溶剂解吸型 | 解吸液:二硫化碳",
    "短时间:0.1L/min; 长时间:0.05L/min",
    ""
  ],
  "正丁醛": [
    "GBZ/T300.99—2017",
    "样品在室温下可保存3d",
    "硅胶管，热解吸型 | 热解吸",
    "短时间:0.1L/min; 长时间:0.05L/min",
    "GBZ/T 300.99—2017 工作场所空气有毒物质测定 第 99 部分：甲醛、乙醛和丁醛/6.正丁醛的热解吸-气相色谱法"
  ],
  "异戊烷": [
    "GBZ/T300.60—2017",
    "样品在室温下可保存7d，置4℃冰箱内可保存更长时间",
    "活性炭管，溶剂解吸型 | 解吸液:二硫化碳",
    "短时间:0.1L/min; 长时间:0.05L/min",
    ""
  ],
  "聚丙烯粉尘": [
    "GBZ/T192.1—2025",
    "长期",
    "丙纶滤膜",
    "短时间:15L/min~40L/min; 长时间:1L/min~5L/min",
    ""
  ],
  "电焊烟尘": [
    "GBZ/T192.1—2025",
    "长期",
    "丙纶滤膜",
    "短时间:15L/min~40L/min; 长时间:1L/min~5L/min",
    ""
  ],
  "炭黑粉尘": [
    "GBZ/T192.1—2025",
    "长期",
    "丙纶滤膜",
    "短时间:15L/min~40L/min; 长时间:1L/min~5L/min",
    ""
  ],
  "水泥粉尘": [
    "GBZ/T192.1—2025",
    "长期",
    "丙纶滤膜",
    "短时间:15L/min~40L/min; 长时间:1L/min~5L/min",
    ""
  ],
  "滑石粉尘": [
    "GBZ/T192.1—2025",
    "长期",
    "丙纶滤膜",
    "短时间:15L/min~40L/min; 长时间:1L/min~5L/min",
    ""
  ],
  "云母粉尘": [
    "GBZ/T192.1—2025",
    "长期",
    "丙纶滤膜",
    "短时间:15L/min~40L/min; 长时间:1L/min~5L/min",
    ""
  ],
  "石墨粉尘": [
    "GBZ/T192.1—2025",
    "长期",
    "丙纶滤膜",
    "短时间:15L/min~40L/min; 长时间:1L/min~5L/min",
    ""
  ],
  "矽尘": [
    "GBZ/T192.1—2025",
    "长期",
    "丙纶滤膜",
    "短时间:15L/min~40L/min; 长时间:1L/min~5L/min",
    ""
  ],
  "煤尘": [
    "GBZ/T192.1—2025",
    "长期",
    "丙纶滤膜",
    "短时间:15L/min~40L/min; 长时间:1L/min~5L/min",
    ""
  ],
  "谷物粉尘": [
    "GBZ/T192.1—2025",
    "长期",
    "丙纶滤膜",
    "短时间:15L/min~40L/min; 长时间:1L/min~5L/min",
    ""
  ],
  "棉尘": [
    "GBZ/T192.1—2025",
    "长期",
    "丙纶滤膜",
    "短时间:15L/min~40L/min; 长时间:1L/min~5L/min",
    ""
  ],
  "木粉尘": [
    "GBZ/T192.1—2025",
    "长期",
    "丙纶滤膜",
    "短时间:15L/min~40L/min; 长时间:1L/min~5L/min",
    ""
  ],
  "氧化镁烟": [
    "GBZ/T300.16—2017",
    "样品在室温下可长期保存",
    "微孔滤膜 | 酸消解",
    "短时间:5L/min",
    ""
  ],
  "三氧化铬": [
    "GBZ/T300.9—2017",
    "样品在室温下可保存3 d",
    "冲击式吸收管 | 显色剂:二苯碳酰二肼",
    "短时间:5L/min; 长时间:1L/min",
    ""
  ],
  "铬酸盐": [
    "GBZ/T300.9—2017",
    "样品在室温下可保存3 d",
    "冲击式吸收管 | 显色剂:二苯碳酰二肼",
    "短时间:5L/min; 长时间:1L/min",
    ""
  ],
  "重铬酸盐": [
    "GBZ/T300.9—2017",
    "样品在室温下可保存3 d",
    "冲击式吸收管 | 显色剂:二苯碳酰二肼",
    "短时间:5L/min; 长时间:1L/min",
    ""
  ],
  "铅尘": [
    "GBZ/T300.15—2017",
    "样品在室温下可长期保存",
    "微孔滤膜 | 酸消解",
    "短时间:5L/min; 长时间:1L/min",
    ""
  ],
  "铅烟": [
    "GBZ/T300.15—2017",
    "样品在室温下可长期保存",
    "微孔滤膜 | 酸消解",
    "短时间:5L/min; 长时间:1L/min",
    ""
  ],
  "2-丁酮": [
    "GBZ/T300.103—2017",
    "样品在室温下可保存7d",
    "活性炭管，溶剂解吸型 | 解吸液:二硫化碳",
    "短时间:0.1L/min; 长时间:0.05L/min",
    ""
  ],
  "1,3-丁二烯": [
    "GBZ/T300.61—2017",
    "样品在4℃冰箱内可保存7 d",
    "活性炭管，溶剂解吸型 | 解吸液:二硫化碳",
    "短时间:0.2L/min; 长时间:0.03L/min",
    "GBZ/T 300.61—2017 工作场所空气有毒物质测定第61部分：丁烯、1,3-丁二烯和二聚环戊二烯/5.1,3-丁二烯的溶剂解吸-气相色谱法"
  ],
  "1,3-二氯丙醇": [
    "GBZ/T300.88—2017",
    "样品在室温下可保存5d",
    "硅胶管，溶剂解吸型",
    "短时间:0.1L/min",
    ""
  ],
  "正丁醇": [
    "GBZ/T300.85—2017",
    "样品在室温下可保存7d",
    "活性炭管，溶剂解吸型 | 解吸液:二硫化碳",
    "短时间:0.1L/min; 长时间:0.05L/min",
    "GBZ/T 300.85—2017工作场所空气有毒物质测定 第 85 部分：丁醇 、戊醇和丙烯醇/4.正丁醇的溶剂解吸-气相色谱法"
  ],
  "苯酚": [
    "GBZ/T160.51—2007",
    "样品在室温下至少可保存10d",
    "硅胶管，溶剂解吸型 | 解吸液:丙酮",
    "短时间:0.3L/min; 长时间:0.05L/min",
    ""
  ],
  "丙烯酸丁酯": [
    "GBZ/T300.127—2017",
    "样品在室温下可保存7d",
    "活性炭管，溶剂解吸型 | 解吸液:二硫化碳",
    "短时间:0.1L/min; 长时间:0.05L/min",
    ""
  ],
  "硫酸": [
    "GBZ/T160.33—2004",
    "样品在室温下可保存3d",
    "微孔滤膜",
    "短时间:1L/min",
    ""
  ],
  "氯化氢": [
    "GBZ/T160.37—2004",
    "在室温下样品可保存7d",
    "多孔玻板吸收管 | 吸收液:碱性溶液",
    "短时间:1L/min",
    ""
  ],
  "三氯丙烷": [
    "GBZ/T160.45—2007",
    "样品在室温下可保存7d",
    "活性炭管，溶剂解吸型 | 解吸液:二硫化碳",
    "短时间:0.3L/min; 长时间:0.05L/min; 个体:0.05L/min",
    ""
  ],
  "三氧化硫": [
    "GBZ/T160.33—2004",
    "样品在室温下可保存3d",
    "微孔滤膜",
    "短时间:1L/min",
    ""
  ],
  "二氯乙烷": [
    "GBZ/T160.45—2007",
    "样品在室温下可保存7d",
    "活性炭管，溶剂解吸型 | 解吸液:二硫化碳",
    "短时间:0.1L/min; 长时间:0.05L/min; 个体:0.05L/min",
    ""
  ],
  "二氯丙醇": [
    "GBZ/T300.88—2017",
    "样品在室温下可保存5d",
    "硅胶管，溶剂解吸型 | 解吸液:乙醇",
    "短时间:0.1L/min",
    ""
  ],
  "氯仿": [
    "GBZ/T300.73—2017",
    "样品在室温下可保存7d",
    "活性炭管，溶剂解吸型 | 解吸液:二硫化碳",
    "短时间:0.1L/min; 长时间:0.05L/min",
    ""
  ],
  "碳酰氯": [
    "GBZ/T160.61—2004",
    "当天测定完毕",
    "多孔玻板吸收管 | 显色剂:苯胺",
    "短时间:0.5L/min",
    ""
  ],
  "氯代苯": [
    "GBZ/T300.81—2017",
    "样品在室温下可保存7d",
    "活性炭管，溶剂解吸型 | 解吸液:二硫化碳",
    "短时间:0.1L/min; 长时间:0.05L/min",
    ""
  ],
  "滴滴涕": [
    "GBZ/T160.77—2004",
    "样品在室温下可长期保存",
    "玻璃纤维滤纸 | 洗脱液:正己烷",
    "短时间:5L/min; 长时间:1L/min; 个体:1L/min",
    ""
  ],
  "六六六": [
    "GBZ/T160.77—2004",
    "样品在室温下可长期保存",
    "玻璃纤维滤纸 | 洗脱液:正己烷",
    "短时间:5L/min; 长时间:1L/min; 个体:1L/min",
    ""
  ],
  "可的松": [
    "GBZ/T160.79—2004",
    "样品在室温下至少可保存7d",
    "微孔滤膜 | 解吸液:甲醇",
    "短时间:5L/min; 长时间:1L/min",
    ""
  ],
  "炔诺孕酮": [
    "GBZ/T160.79—2004",
    "样品在室温下至少可保存7d",
    "微孔滤膜 | 解吸液:甲醇",
    "短时间:5L/min; 长时间:1L/min",
    ""
  ],
  "磺胺": [
    "GBZ/T160.79—2004",
    "样品在室温下至少可保存7d",
    "微孔滤膜 | 解吸液:甲醇",
    "短时间:5L/min; 长时间:1L/min",
    ""
  ],
  "甲胺磷": [
    "GBZ/T300.149—2017",
    "样品在冰箱内可保存7d",
    "硅胶管，溶剂解吸型 | 解吸液:丙酮",
    "短时间:0.5L/min; 长时间:0.05L/min",
    ""
  ],
  "锕系元素": [
    "GBZ/T300.33—2017",
    "样品在常温下可保存7d",
    "微孔滤膜 | 酸消解",
    "短时间:5L/min; 长时间:1L/min",
    ""
  ],
  "铜尘": [
    "GBZ/T300.11—2017",
    "样品在室温下可长期保存",
    "微孔滤膜 | 酸消解",
    "短时间:5L/min; 长时间:1L/min",
    ""
  ],
  "铜烟": [
    "GBZ/T300.11—2017",
    "样品在室温下可长期保存",
    "微孔滤膜 | 酸消解",
    "短时间:5L/min; 长时间:1L/min",
    ""
  ],
  "硫酸钡": [
    "GBZ/T300.3—2017",
    "样品在室温下可长期保存",
    "微孔滤膜 | 酸消解",
    "短时间:5L/min; 长时间:1L/min",
    ""
  ],
  "二氧化锰": [
    "GBZ/T300.17—2017",
    "样品在室温下可长期保存",
    "微孔滤膜 | 酸消解",
    "短时间:5L/min; 长时间:1L/min",
    ""
  ],
  "高锰酸钾": [
    "GBZ/T300.21—2017",
    "样品在室温下可长期保存",
    "微孔滤膜 | 洗脱液:水",
    "短时间:5L/min; 长时间:1L/min",
    ""
  ],
  "碳酸锶": [
    "GBZ/T300.23—2017",
    "样品在室温下可长时间保存",
    "微孔滤膜 | 酸消解",
    "短时间:5L/min; 长时间:1L/min",
    ""
  ],
  "硝酸锶": [
    "GBZ/T300.23—2017",
    "样品在室温下可长时间保存",
    "微孔滤膜 | 酸消解",
    "短时间:5L/min; 长时间:1L/min",
    ""
  ],
  "氧化锶": [
    "GBZ/T300.23—2017",
    "样品在室温下可长时间保存",
    "微孔滤膜 | 酸消解",
    "短时间:5L/min; 长时间:1L/min",
    ""
  ],
  "偏锆酸钠": [
    "GBZ/T300.32—2017",
    "样品在室温下可长期保存",
    "微孔滤膜 | 显色剂:二甲酚橙",
    "短时间:5L/min; 长时间:1L/min",
    ""
  ],
  "二氧化锆": [
    "GBZ/T300.32—2017",
    "样品在室温下可长期保存",
    "微孔滤膜 | 显色剂:二甲酚橙",
    "短时间:5L/min; 长时间:1L/min",
    ""
  ],
  "氧化铅": [
    "GBZ/T300.15—2017",
    "样品在室温下可长期保存",
    "微孔滤膜 | 酸消解",
    "短时间:5L/min; 长时间:1L/min",
    ""
  ],
  "硫化铅": [
    "GBZ/T300.15—2017",
    "样品在室温下可长期保存",
    "微孔滤膜 | 酸消解",
    "短时间:5L/min; 长时间:1L/min",
    ""
  ],
  "氧化钴": [
    "GBZ/T300.10—2017",
    "样品在室温下可长期保存",
    "微孔滤膜 | 酸消解",
    "短时间:5L/min",
    ""
  ],
  "氧化铜": [
    "GBZ/T300.11—2017",
    "样品在室温下可长期保存",
    "微孔滤膜 | 酸消解",
    "短时间:5L/min; 长时间:1L/min",
    ""
  ],
  "氧化铟": [
    "GBZ/T300.13—2017",
    "样品在常温下可长期保存",
    "微孔滤膜 | 酸消解",
    "短时间:5L/min; 长时间:1L/min",
    ""
  ],
  "氧化锑": [
    "GBZ/T300.2—2017",
    "样品在室温下可长期保存",
    "微孔滤膜 | 酸消解",
    "短时间:5L/min; 长时间:1L/min",
    ""
  ],
  "氧化镉": [
    "GBZ/T300.6—2017",
    "样品在室温下可长期保存",
    "微孔滤膜 | 酸消解",
    "短时间:5L/min; 长时间:1L/min",
    ""
  ],
  "有机汞": [
    "GBZ/T300.18—2017",
    "样品24 h内测定",
    "大型气泡吸收管 | 吸收液:酸性高锰酸钾",
    "短时间:0.5L/min",
    ""
  ],
  "盐酸": [
    "GBZ/T160.37—2004",
    "在室温下样品可保存7d",
    "多孔玻板吸收管 | 吸收液:碱性溶液",
    "短时间:1L/min",
    ""
  ],
  "金属粉尘": [
    "GBZ/T192.1—2025",
    "长期",
    "丙纶滤膜",
    "短时间:15L/min~40L/min; 长时间:1L/min~5L/min",
    ""
  ],
  "其他粉尘（金属粉尘）": [
    "GBZ/T192.1—2025",
    "长期",
    "丙纶滤膜",
    "短时间:15L/min~40L/min; 长时间:1L/min~5L/min",
    ""
  ]
}